Workbook

Sheet Mode d'emploi
A1: SPHORIX FRANCE | TABLEAU DE SUIVI DES DEPENSES
A3: Centraliser, catégoriser et analyser les charges de votre activité.
A5: MODELE AVEC DONNEES FICTIVES Les montants sont fictifs. Utilisez ce modèle comme base de suivi interne. Version 1.0 - Septembre 2026

Sheet Catégories
A1: Catégories de dépenses
A2: Achats
A3: Salaires
A4: Loyer
A5: Transport
A6: Logiciels
A7: Communication
A8: Taxes
A9: Autre

Sheet Saisie des dépenses
A1: Date | B1: Fournisseur | C1: Catégorie | D1: Description | E1: Montant TTC | F1: Payé ?
A2: 46025.958 | B2: Fournisseur A | C2: Achats | D2: Matières premières | E2: 840 | F2: Oui
A3: 46036.958 | B3: Outil B | C3: Logiciels | D3: Abonnement annuel | E3: 240 | F3: Oui
A4: 46063.958 | B4: Prestataire C | C4: Communication | D4: Impression supports | E4: 390 | F4: Non

Sheet Synthèse mensuelle
A1: Mois | B1: Total dépenses | C1: Dépenses payées | D1: Dépenses à payer
A2: 46022.958 | B2: =SUMIFS('Saisie des dépenses'!$E:$E,'Saisie des dépenses'!$A:$A,">="&A2,'Saisie des dépenses'!$A:$A,"<"&EDATE(A2,1)) | C2: =SUMIFS('Saisie des dépenses'!$E:$E,'Saisie des dépenses'!$A:$A,">="&A2,'Saisie des dépenses'!$A:$A,"<"&EDATE(A2,1),'Saisie des dépenses'!$F:$F,"Oui") | D2: =B2-C2
A3: 46053.958 | B3: =SUMIFS('Saisie des dépenses'!$E:$E,'Saisie des dépenses'!$A:$A,">="&A3,'Saisie des dépenses'!$A:$A,"<"&EDATE(A3,1)) | C3: =SUMIFS('Saisie des dépenses'!$E:$E,'Saisie des dépenses'!$A:$A,">="&A3,'Saisie des dépenses'!$A:$A,"<"&EDATE(A3,1),'Saisie des dépenses'!$F:$F,"Oui") | D3: =B3-C3
A4: 46081.958 | B4: =SUMIFS('Saisie des dépenses'!$E:$E,'Saisie des dépenses'!$A:$A,">="&A4,'Saisie des dépenses'!$A:$A,"<"&EDATE(A4,1)) | C4: =SUMIFS('Saisie des dépenses'!$E:$E,'Saisie des dépenses'!$A:$A,">="&A4,'Saisie des dépenses'!$A:$A,"<"&EDATE(A4,1),'Saisie des dépenses'!$F:$F,"Oui") | D4: =B4-C4
A5: 46112.917 | B5: =SUMIFS('Saisie des dépenses'!$E:$E,'Saisie des dépenses'!$A:$A,">="&A5,'Saisie des dépenses'!$A:$A,"<"&EDATE(A5,1)) | C5: =SUMIFS('Saisie des dépenses'!$E:$E,'Saisie des dépenses'!$A:$A,">="&A5,'Saisie des dépenses'!$A:$A,"<"&EDATE(A5,1),'Saisie des dépenses'!$F:$F,"Oui") | D5: =B5-C5
A6: 46142.917 | B6: =SUMIFS('Saisie des dépenses'!$E:$E,'Saisie des dépenses'!$A:$A,">="&A6,'Saisie des dépenses'!$A:$A,"<"&EDATE(A6,1)) | C6: =SUMIFS('Saisie des dépenses'!$E:$E,'Saisie des dépenses'!$A:$A,">="&A6,'Saisie des dépenses'!$A:$A,"<"&EDATE(A6,1),'Saisie des dépenses'!$F:$F,"Oui") | D6: =B6-C6
A7: 46173.917 | B7: =SUMIFS('Saisie des dépenses'!$E:$E,'Saisie des dépenses'!$A:$A,">="&A7,'Saisie des dépenses'!$A:$A,"<"&EDATE(A7,1)) | C7: =SUMIFS('Saisie des dépenses'!$E:$E,'Saisie des dépenses'!$A:$A,">="&A7,'Saisie des dépenses'!$A:$A,"<"&EDATE(A7,1),'Saisie des dépenses'!$F:$F,"Oui") | D7: =B7-C7
A8: 46203.917 | B8: =SUMIFS('Saisie des dépenses'!$E:$E,'Saisie des dépenses'!$A:$A,">="&A8,'Saisie des dépenses'!$A:$A,"<"&EDATE(A8,1)) | C8: =SUMIFS('Saisie des dépenses'!$E:$E,'Saisie des dépenses'!$A:$A,">="&A8,'Saisie des dépenses'!$A:$A,"<"&EDATE(A8,1),'Saisie des dépenses'!$F:$F,"Oui") | D8: =B8-C8
A9: 46234.917 | B9: =SUMIFS('Saisie des dépenses'!$E:$E,'Saisie des dépenses'!$A:$A,">="&A9,'Saisie des dépenses'!$A:$A,"<"&EDATE(A9,1)) | C9: =SUMIFS('Saisie des dépenses'!$E:$E,'Saisie des dépenses'!$A:$A,">="&A9,'Saisie des dépenses'!$A:$A,"<"&EDATE(A9,1),'Saisie des dépenses'!$F:$F,"Oui") | D9: =B9-C9
A10: 46265.917 | B10: =SUMIFS('Saisie des dépenses'!$E:$E,'Saisie des dépenses'!$A:$A,">="&A10,'Saisie des dépenses'!$A:$A,"<"&EDATE(A10,1)) | C10: =SUMIFS('Saisie des dépenses'!$E:$E,'Saisie des dépenses'!$A:$A,">="&A10,'Saisie des dépenses'!$A:$A,"<"&EDATE(A10,1),'Saisie des dépenses'!$F:$F,"Oui") | D10: =B10-C10
A11: 46295.917 | B11: =SUMIFS('Saisie des dépenses'!$E:$E,'Saisie des dépenses'!$A:$A,">="&A11,'Saisie des dépenses'!$A:$A,"<"&EDATE(A11,1)) | C11: =SUMIFS('Saisie des dépenses'!$E:$E,'Saisie des dépenses'!$A:$A,">="&A11,'Saisie des dépenses'!$A:$A,"<"&EDATE(A11,1),'Saisie des dépenses'!$F:$F,"Oui") | D11: =B11-C11
A12: 46326.958 | B12: =SUMIFS('Saisie des dépenses'!$E:$E,'Saisie des dépenses'!$A:$A,">="&A12,'Saisie des dépenses'!$A:$A,"<"&EDATE(A12,1)) | C12: =SUMIFS('Saisie des dépenses'!$E:$E,'Saisie des dépenses'!$A:$A,">="&A12,'Saisie des dépenses'!$A:$A,"<"&EDATE(A12,1),'Saisie des dépenses'!$F:$F,"Oui") | D12: =B12-C12
A13: 46356.958 | B13: =SUMIFS('Saisie des dépenses'!$E:$E,'Saisie des dépenses'!$A:$A,">="&A13,'Saisie des dépenses'!$A:$A,"<"&EDATE(A13,1)) | C13: =SUMIFS('Saisie des dépenses'!$E:$E,'Saisie des dépenses'!$A:$A,">="&A13,'Saisie des dépenses'!$A:$A,"<"&EDATE(A13,1),'Saisie des dépenses'!$F:$F,"Oui") | D13: =B13-C13
A15: Outil de suivi interne. Vérifiez vos obligations comptables et fiscales avec votre professionnel habituel.

Sheet Analyse par catégorie
A1: Catégorie | B1: Total
A2: Achats | B2: =SUMIF('Saisie des dépenses'!$C:$C,A2,'Saisie des dépenses'!$E:$E)
A3: Salaires | B3: =SUMIF('Saisie des dépenses'!$C:$C,A3,'Saisie des dépenses'!$E:$E)
A4: Loyer | B4: =SUMIF('Saisie des dépenses'!$C:$C,A4,'Saisie des dépenses'!$E:$E)
A5: Transport | B5: =SUMIF('Saisie des dépenses'!$C:$C,A5,'Saisie des dépenses'!$E:$E)
A6: Logiciels | B6: =SUMIF('Saisie des dépenses'!$C:$C,A6,'Saisie des dépenses'!$E:$E)
A7: Communication | B7: =SUMIF('Saisie des dépenses'!$C:$C,A7,'Saisie des dépenses'!$E:$E)
A8: Taxes | B8: =SUMIF('Saisie des dépenses'!$C:$C,A8,'Saisie des dépenses'!$E:$E)
A9: Autre | B9: =SUMIF('Saisie des dépenses'!$C:$C,A9,'Saisie des dépenses'!$E:$E)
