Workbook

Sheet 01_ACCUEIL
A1: SADesk | TABLEAU DE SUIVI DE TRÉSORERIE
A3: Pilotez votre trésorerie simplement.
A5: 1. Configurez vos paramètres • 2. Saisissez vos flux • 3. Consultez vos prévisions et alertes
A7: 💰 SAISIR MES FLUX | C7: 📊 VOIR MA TRÉSORERIE | E7: ⚠ VOIR MES ALERTES
A12: Les montants d'exemple sont fictifs. Les cellules bleues sont à renseigner ; les cellules blanches sont calculées automatiquement.
A16: Dernière mise à jour : 19/09/2026 · Outil de gestion, non comptable.

Sheet 02_PARAMETRES
A1: PARAMÈTRES DE L'ENTREPRISE | B1: Valeur
A2: Nom de l'entreprise | B2: Entreprise exemple
A3: Période de suivi | B3: 90 jours
A4: Devise | B4: EUR
A6: TRÉSORERIE | B6: Valeur
A7: Solde initial | B7: 25000
A8: Seuil de sécurité | B8: 10000
A9: Date du solde initial | B9: 46265.917

Sheet 03_FLUX
A1: Saisissez un montant toujours positif : le type de flux détermine automatiquement son impact sur la trésorerie.
A2: Date | B2: Type | C2: Catégorie | D2: Libellé | E2: Montant | F2: Statut | G2: Commentaire | H2: Impact trésorerie
A3: 46269.917 | B3: Encaissement | C3: Ventes | D3: Facture ABC | E3: 3500 | F3: Prévu | G3: Exemple fictif | H3: =IF(B3="Encaissement",E3,-E3)
A4: 46271.917 | B4: Décaissement | C4: Fournisseurs | D4: Matériaux | E4: 1200 | F4: Prévu | G4: Exemple fictif | H4: =IF(B4="Encaissement",E4,-E4)
A5: 46274.917 | B5: Décaissement | C5: Salaires | D5: Salaires | E5: 5000 | F5: Prévu | G5: Exemple fictif | H5: =IF(B5="Encaissement",E5,-E5)
A6: 46279.917 | B6: Encaissement | C6: Ventes | D6: Facture XYZ | E6: 2800 | F6: Réalisé | G6: Exemple fictif | H6: =IF(B6="Encaissement",E6,-E6)
H7: =IF(B7="","",IF(B7="Encaissement",E7,-E7))
H8: =IF(B8="","",IF(B8="Encaissement",E8,-E8))
H9: =IF(B9="","",IF(B9="Encaissement",E9,-E9))
H10: =IF(B10="","",IF(B10="Encaissement",E10,-E10))
H11: =IF(B11="","",IF(B11="Encaissement",E11,-E11))
H12: =IF(B12="","",IF(B12="Encaissement",E12,-E12))
H13: =IF(B13="","",IF(B13="Encaissement",E13,-E13))
H14: =IF(B14="","",IF(B14="Encaissement",E14,-E14))
H15: =IF(B15="","",IF(B15="Encaissement",E15,-E15))
H16: =IF(B16="","",IF(B16="Encaissement",E16,-E16))
H17: =IF(B17="","",IF(B17="Encaissement",E17,-E17))
H18: =IF(B18="","",IF(B18="Encaissement",E18,-E18))
... H502: =IF(B502="","",IF(B502="Encaissement",E502,-E502))

Sheet 04_TABLEAU_DE_BORD
A1: TABLEAU DE BORD DE TRÉSORERIE
A4: TRÉSORERIE ACTUELLE | B4: ='02_PARAMETRES'!B7+SUMIFS('03_FLUX'!$H$3:$H$502,'03_FLUX'!$F$3:$F$502,"Réalisé") | D4: PRÉVISION À 30 JOURS | E4: ='05_PREVISION'!F31
A8: PRÉVISION À 60 JOURS | B8: ='05_PREVISION'!F61 | D8: PRÉVISION À 90 JOURS | E8: ='05_PREVISION'!F91
A12: SEUIL DE SÉCURITÉ | B12: ='02_PARAMETRES'!B8 | D12: ÉCART AU SEUIL À 90 J. | E12: =E8-B12
A16: POINT DE TENSION PRÉVISIONNEL | B16: =IFERROR(INDEX('05_PREVISION'!A2:A91,MATCH(TRUE,'05_PREVISION'!F2:F91<'05_PREVISION'!G2:G91,0)),"Aucun sur 90 jours") | D16: DÉCAISSEMENTS À 7 JOURS | E16: =SUM('05_PREVISION'!C2:C8)
A20: =IF(MIN('05_PREVISION'!F2:F91)<'02_PARAMETRES'!B8,"⚠ ALERTE : votre trésorerie prévisionnelle passe sous votre seuil de sécurité. Consultez le point de tension et les flux à venir.",IF(MIN('05_PREVISION'!F2:F91)<'02_PARAMETRES'!B8*1.2,"⚠ VIGILANCE : votre trésorerie prévisionnelle se rapproche de votre seuil de sécurité.","✓ Situation normale : votre trésorerie prévisionnelle reste supérieure à votre seuil de sécurité."))
A25: ="Situation de trésorerie : solde actuel "&TEXT(B4,"#,##0.00 €")&". Sur les 90 prochains jours, le minimum prévisionnel est "&TEXT(MIN('05_PREVISION'!F2:F91),"#,##0.00 €")&"."

Sheet 05_PREVISION
A1: Date | B1: Encaissements prévus | C1: Décaissements prévus | D1: Encaissements réalisés | E1: Décaissements réalisés | F1: Solde prévisionnel | G1: Seuil de sécurité | H1: Alerte
A2: ='02_PARAMETRES'!B9 | B2: =SUMIFS('03_FLUX'!$E$3:$E$502,'03_FLUX'!$A$3:$A$502,A2,'03_FLUX'!$B$3:$B$502,"Encaissement",'03_FLUX'!$F$3:$F$502,"Prévu") | C2: =SUMIFS('03_FLUX'!$E$3:$E$502,'03_FLUX'!$A$3:$A$502,A2,'03_FLUX'!$B$3:$B$502,"Décaissement",'03_FLUX'!$F$3:$F$502,"Prévu") | D2: =SUMIFS('03_FLUX'!$E$3:$E$502,'03_FLUX'!$A$3:$A$502,A2,'03_FLUX'!$B$3:$B$502,"Encaissement",'03_FLUX'!$F$3:$F$502,"Réalisé") | E2: =SUMIFS('03_FLUX'!$E$3:$E$502,'03_FLUX'!$A$3:$A$502,A2,'03_FLUX'!$B$3:$B$502,"Décaissement",'03_FLUX'!$F$3:$F$502,"Réalisé") | F2: ='02_PARAMETRES'!B7+D2-E2+B2-C2 | G2: ='02_PARAMETRES'!B8 | H2: =IF(F2<G2,"ALERTE",IF(F2<G2*1.2,"VIGILANCE","NORMAL"))
A3: =A2+1 | B3: =SUMIFS('03_FLUX'!$E$3:$E$502,'03_FLUX'!$A$3:$A$502,A3,'03_FLUX'!$B$3:$B$502,"Encaissement",'03_FLUX'!$F$3:$F$502,"Prévu") | C3: =SUMIFS('03_FLUX'!$E$3:$E$502,'03_FLUX'!$A$3:$A$502,A3,'03_FLUX'!$B$3:$B$502,"Décaissement",'03_FLUX'!$F$3:$F$502,"Prévu") | D3: =SUMIFS('03_FLUX'!$E$3:$E$502,'03_FLUX'!$A$3:$A$502,A3,'03_FLUX'!$B$3:$B$502,"Encaissement",'03_FLUX'!$F$3:$F$502,"Réalisé") | E3: =SUMIFS('03_FLUX'!$E$3:$E$502,'03_FLUX'!$A$3:$A$502,A3,'03_FLUX'!$B$3:$B$502,"Décaissement",'03_FLUX'!$F$3:$F$502,"Réalisé") | F3: =F2+D3-E3+B3-C3 | G3: ='02_PARAMETRES'!B8 | H3: =IF(F3<G3,"ALERTE",IF(F3<G3*1.2,"VIGILANCE","NORMAL"))
A4: =A3+1 | B4: =SUMIFS('03_FLUX'!$E$3:$E$502,'03_FLUX'!$A$3:$A$502,A4,'03_FLUX'!$B$3:$B$502,"Encaissement",'03_FLUX'!$F$3:$F$502,"Prévu") | C4: =SUMIFS('03_FLUX'!$E$3:$E$502,'03_FLUX'!$A$3:$A$502,A4,'03_FLUX'!$B$3:$B$502,"Décaissement",'03_FLUX'!$F$3:$F$502,"Prévu") | D4: =SUMIFS('03_FLUX'!$E$3:$E$502,'03_FLUX'!$A$3:$A$502,A4,'03_FLUX'!$B$3:$B$502,"Encaissement",'03_FLUX'!$F$3:$F$502,"Réalisé") | E4: =SUMIFS('03_FLUX'!$E$3:$E$502,'03_FLUX'!$A$3:$A$502,A4,'03_FLUX'!$B$3:$B$502,"Décaissement",'03_FLUX'!$F$3:$F$502,"Réalisé") | F4: =F3+D4-E4+B4-C4 | G4: ='02_PARAMETRES'!B8 | H4: =IF(F4<G4,"ALERTE",IF(F4<G4*1.2,"VIGILANCE","NORMAL"))
A5: =A4+1 | B5: =SUMIFS('03_FLUX'!$E$3:$E$502,'03_FLUX'!$A$3:$A$502,A5,'03_FLUX'!$B$3:$B$502,"Encaissement",'03_FLUX'!$F$3:$F$502,"Prévu") | C5: =SUMIFS('03_FLUX'!$E$3:$E$502,'03_FLUX'!$A$3:$A$502,A5,'03_FLUX'!$B$3:$B$502,"Décaissement",'03_FLUX'!$F$3:$F$502,"Prévu") | D5: =SUMIFS('03_FLUX'!$E$3:$E$502,'03_FLUX'!$A$3:$A$502,A5,'03_FLUX'!$B$3:$B$502,"Encaissement",'03_FLUX'!$F$3:$F$502,"Réalisé") | E5: =SUMIFS('03_FLUX'!$E$3:$E$502,'03_FLUX'!$A$3:$A$502,A5,'03_FLUX'!$B$3:$B$502,"Décaissement",'03_FLUX'!$F$3:$F$502,"Réalisé") | F5: =F4+D5-E5+B5-C5 | G5: ='02_PARAMETRES'!B8 | H5: =IF(F5<G5,"ALERTE",IF(F5<G5*1.2,"VIGILANCE","NORMAL"))
A6: =A5+1 | B6: =SUMIFS('03_FLUX'!$E$3:$E$502,'03_FLUX'!$A$3:$A$502,A6,'03_FLUX'!$B$3:$B$502,"Encaissement",'03_FLUX'!$F$3:$F$502,"Prévu") | C6: =SUMIFS('03_FLUX'!$E$3:$E$502,'03_FLUX'!$A$3:$A$502,A6,'03_FLUX'!$B$3:$B$502,"Décaissement",'03_FLUX'!$F$3:$F$502,"Prévu") | D6: =SUMIFS('03_FLUX'!$E$3:$E$502,'03_FLUX'!$A$3:$A$502,A6,'03_FLUX'!$B$3:$B$502,"Encaissement",'03_FLUX'!$F$3:$F$502,"Réalisé") | E6: =SUMIFS('03_FLUX'!$E$3:$E$502,'03_FLUX'!$A$3:$A$502,A6,'03_FLUX'!$B$3:$B$502,"Décaissement",'03_FLUX'!$F$3:$F$502,"Réalisé") | F6: =F5+D6-E6+B6-C6 | G6: ='02_PARAMETRES'!B8 | H6: =IF(F6<G6,"ALERTE",IF(F6<G6*1.2,"VIGILANCE","NORMAL"))
A7: =A6+1 | B7: =SUMIFS('03_FLUX'!$E$3:$E$502,'03_FLUX'!$A$3:$A$502,A7,'03_FLUX'!$B$3:$B$502,"Encaissement",'03_FLUX'!$F$3:$F$502,"Prévu") | C7: =SUMIFS('03_FLUX'!$E$3:$E$502,'03_FLUX'!$A$3:$A$502,A7,'03_FLUX'!$B$3:$B$502,"Décaissement",'03_FLUX'!$F$3:$F$502,"Prévu") | D7: =SUMIFS('03_FLUX'!$E$3:$E$502,'03_FLUX'!$A$3:$A$502,A7,'03_FLUX'!$B$3:$B$502,"Encaissement",'03_FLUX'!$F$3:$F$502,"Réalisé") | E7: =SUMIFS('03_FLUX'!$E$3:$E$502,'03_FLUX'!$A$3:$A$502,A7,'03_FLUX'!$B$3:$B$502,"Décaissement",'03_FLUX'!$F$3:$F$502,"Réalisé") | F7: =F6+D7-E7+B7-C7 | G7: ='02_PARAMETRES'!B8 | H7: =IF(F7<G7,"ALERTE",IF(F7<G7*1.2,"VIGILANCE","NORMAL"))
A8: =A7+1 | B8: =SUMIFS('03_FLUX'!$E$3:$E$502,'03_FLUX'!$A$3:$A$502,A8,'03_FLUX'!$B$3:$B$502,"Encaissement",'03_FLUX'!$F$3:$F$502,"Prévu") | C8: =SUMIFS('03_FLUX'!$E$3:$E$502,'03_FLUX'!$A$3:$A$502,A8,'03_FLUX'!$B$3:$B$502,"Décaissement",'03_FLUX'!$F$3:$F$502,"Prévu") | D8: =SUMIFS('03_FLUX'!$E$3:$E$502,'03_FLUX'!$A$3:$A$502,A8,'03_FLUX'!$B$3:$B$502,"Encaissement",'03_FLUX'!$F$3:$F$502,"Réalisé") | E8: =SUMIFS('03_FLUX'!$E$3:$E$502,'03_FLUX'!$A$3:$A$502,A8,'03_FLUX'!$B$3:$B$502,"Décaissement",'03_FLUX'!$F$3:$F$502,"Réalisé") | F8: =F7+D8-E8+B8-C8 | G8: ='02_PARAMETRES'!B8 | H8: =IF(F8<G8,"ALERTE",IF(F8<G8*1.2,"VIGILANCE","NORMAL"))
A9: =A8+1 | B9: =SUMIFS('03_FLUX'!$E$3:$E$502,'03_FLUX'!$A$3:$A$502,A9,'03_FLUX'!$B$3:$B$502,"Encaissement",'03_FLUX'!$F$3:$F$502,"Prévu") | C9: =SUMIFS('03_FLUX'!$E$3:$E$502,'03_FLUX'!$A$3:$A$502,A9,'03_FLUX'!$B$3:$B$502,"Décaissement",'03_FLUX'!$F$3:$F$502,"Prévu") | D9: =SUMIFS('03_FLUX'!$E$3:$E$502,'03_FLUX'!$A$3:$A$502,A9,'03_FLUX'!$B$3:$B$502,"Encaissement",'03_FLUX'!$F$3:$F$502,"Réalisé") | E9: =SUMIFS('03_FLUX'!$E$3:$E$502,'03_FLUX'!$A$3:$A$502,A9,'03_FLUX'!$B$3:$B$502,"Décaissement",'03_FLUX'!$F$3:$F$502,"Réalisé") | F9: =F8+D9-E9+B9-C9 | G9: ='02_PARAMETRES'!B8 | H9: =IF(F9<G9,"ALERTE",IF(F9<G9*1.2,"VIGILANCE","NORMAL"))
A10: =A9+1 | B10: =SUMIFS('03_FLUX'!$E$3:$E$502,'03_FLUX'!$A$3:$A$502,A10,'03_FLUX'!$B$3:$B$502,"Encaissement",'03_FLUX'!$F$3:$F$502,"Prévu") | C10: =SUMIFS('03_FLUX'!$E$3:$E$502,'03_FLUX'!$A$3:$A$502,A10,'03_FLUX'!$B$3:$B$502,"Décaissement",'03_FLUX'!$F$3:$F$502,"Prévu") | D10: =SUMIFS('03_FLUX'!$E$3:$E$502,'03_FLUX'!$A$3:$A$502,A10,'03_FLUX'!$B$3:$B$502,"Encaissement",'03_FLUX'!$F$3:$F$502,"Réalisé") | E10: =SUMIFS('03_FLUX'!$E$3:$E$502,'03_FLUX'!$A$3:$A$502,A10,'03_FLUX'!$B$3:$B$502,"Décaissement",'03_FLUX'!$F$3:$F$502,"Réalisé") | F10: =F9+D10-E10+B10-C10 | G10: ='02_PARAMETRES'!B8 | H10: =IF(F10<G10,"ALERTE",IF(F10<G10*1.2,"VIGILANCE","NORMAL"))
A11: =A10+1 | B11: =SUMIFS('03_FLUX'!$E$3:$E$502,'03_FLUX'!$A$3:$A$502,A11,'03_FLUX'!$B$3:$B$502,"Encaissement",'03_FLUX'!$F$3:$F$502,"Prévu") | C11: =SUMIFS('03_FLUX'!$E$3:$E$502,'03_FLUX'!$A$3:$A$502,A11,'03_FLUX'!$B$3:$B$502,"Décaissement",'03_FLUX'!$F$3:$F$502,"Prévu") | D11: =SUMIFS('03_FLUX'!$E$3:$E$502,'03_FLUX'!$A$3:$A$502,A11,'03_FLUX'!$B$3:$B$502,"Encaissement",'03_FLUX'!$F$3:$F$502,"Réalisé") | E11: =SUMIFS('03_FLUX'!$E$3:$E$502,'03_FLUX'!$A$3:$A$502,A11,'03_FLUX'!$B$3:$B$502,"Décaissement",'03_FLUX'!$F$3:$F$502,"Réalisé") | F11: =F10+D11-E11+B11-C11 | G11: ='02_PARAMETRES'!B8 | H11: =IF(F11<G11,"ALERTE",IF(F11<G11*1.2,"VIGILANCE","NORMAL"))
A12: =A11+1 | B12: =SUMIFS('03_FLUX'!$E$3:$E$502,'03_FLUX'!$A$3:$A$502,A12,'03_FLUX'!$B$3:$B$502,"Encaissement",'03_FLUX'!$F$3:$F$502,"Prévu") | C12: =SUMIFS('03_FLUX'!$E$3:$E$502,'03_FLUX'!$A$3:$A$502,A12,'03_FLUX'!$B$3:$B$502,"Décaissement",'03_FLUX'!$F$3:$F$502,"Prévu") | D12: =SUMIFS('03_FLUX'!$E$3:$E$502,'03_FLUX'!$A$3:$A$502,A12,'03_FLUX'!$B$3:$B$502,"Encaissement",'03_FLUX'!$F$3:$F$502,"Réalisé") | E12: =SUMIFS('03_FLUX'!$E$3:$E$502,'03_FLUX'!$A$3:$A$502,A12,'03_FLUX'!$B$3:$B$502,"Décaissement",'03_FLUX'!$F$3:$F$502,"Réalisé") | F12: =F11+D12-E12+B12-C12 | G12: ='02_PARAMETRES'!B8 | H12: =IF(F12<G12,"ALERTE",IF(F12<G12*1.2,"VIGILANCE","NORMAL"))
A13: =A12+1 | B13: =SUMIFS('03_FLUX'!$E$3:$E$502,'03_FLUX'!$A$3:$A$502,A13,'03_FLUX'!$B$3:$B$502,"Encaissement",'03_FLUX'!$F$3:$F$502,"Prévu") | C13: =SUMIFS('03_FLUX'!$E$3:$E$502,'03_FLUX'!$A$3:$A$502,A13,'03_FLUX'!$B$3:$B$502,"Décaissement",'03_FLUX'!$F$3:$F$502,"Prévu") | D13: =SUMIFS('03_FLUX'!$E$3:$E$502,'03_FLUX'!$A$3:$A$502,A13,'03_FLUX'!$B$3:$B$502,"Encaissement",'03_FLUX'!$F$3:$F$502,"Réalisé") | E13: =SUMIFS('03_FLUX'!$E$3:$E$502,'03_FLUX'!$A$3:$A$502,A13,'03_FLUX'!$B$3:$B$502,"Décaissement",'03_FLUX'!$F$3:$F$502,"Réalisé") | F13: =F12+D13-E13+B13-C13 | G13: ='02_PARAMETRES'!B8 | H13: =IF(F13<G13,"ALERTE",IF(F13<G13*1.2,"VIGILANCE","NORMAL"))
A14: =A13+1 | B14: =SUMIFS('03_FLUX'!$E$3:$E$502,'03_FLUX'!$A$3:$A$502,A14,'03_FLUX'!$B$3:$B$502,"Encaissement",'03_FLUX'!$F$3:$F$502,"Prévu") | C14: =SUMIFS('03_FLUX'!$E$3:$E$502,'03_FLUX'!$A$3:$A$502,A14,'03_FLUX'!$B$3:$B$502,"Décaissement",'03_FLUX'!$F$3:$F$502,"Prévu") | D14: =SUMIFS('03_FLUX'!$E$3:$E$502,'03_FLUX'!$A$3:$A$502,A14,'03_FLUX'!$B$3:$B$502,"Encaissement",'03_FLUX'!$F$3:$F$502,"Réalisé") | E14: =SUMIFS('03_FLUX'!$E$3:$E$502,'03_FLUX'!$A$3:$A$502,A14,'03_FLUX'!$B$3:$B$502,"Décaissement",'03_FLUX'!$F$3:$F$502,"Réalisé") | F14: =F13+D14-E14+B14-C14 | G14: ='02_PARAMETRES'!B8 | H14: =IF(F14<G14,"ALERTE",IF(F14<G14*1.2,"VIGILANCE","NORMAL"))
A15: =A14+1 | B15: =SUMIFS('03_FLUX'!$E$3:$E$502,'03_FLUX'!$A$3:$A$502,A15,'03_FLUX'!$B$3:$B$502,"Encaissement",'03_FLUX'!$F$3:$F$502,"Prévu") | C15: =SUMIFS('03_FLUX'!$E$3:$E$502,'03_FLUX'!$A$3:$A$502,A15,'03_FLUX'!$B$3:$B$502,"Décaissement",'03_FLUX'!$F$3:$F$502,"Prévu") | D15: =SUMIFS('03_FLUX'!$E$3:$E$502,'03_FLUX'!$A$3:$A$502,A15,'03_FLUX'!$B$3:$B$502,"Encaissement",'03_FLUX'!$F$3:$F$502,"Réalisé") | E15: =SUMIFS('03_FLUX'!$E$3:$E$502,'03_FLUX'!$A$3:$A$502,A15,'03_FLUX'!$B$3:$B$502,"Décaissement",'03_FLUX'!$F$3:$F$502,"Réalisé") | F15: =F14+D15-E15+B15-C15 | G15: ='02_PARAMETRES'!B8 | H15: =IF(F15<G15,"ALERTE",IF(F15<G15*1.2,"VIGILANCE","NORMAL"))
A16: =A15+1 | B16: =SUMIFS('03_FLUX'!$E$3:$E$502,'03_FLUX'!$A$3:$A$502,A16,'03_FLUX'!$B$3:$B$502,"Encaissement",'03_FLUX'!$F$3:$F$502,"Prévu") | C16: =SUMIFS('03_FLUX'!$E$3:$E$502,'03_FLUX'!$A$3:$A$502,A16,'03_FLUX'!$B$3:$B$502,"Décaissement",'03_FLUX'!$F$3:$F$502,"Prévu") | D16: =SUMIFS('03_FLUX'!$E$3:$E$502,'03_FLUX'!$A$3:$A$502,A16,'03_FLUX'!$B$3:$B$502,"Encaissement",'03_FLUX'!$F$3:$F$502,"Réalisé") | E16: =SUMIFS('03_FLUX'!$E$3:$E$502,'03_FLUX'!$A$3:$A$502,A16,'03_FLUX'!$B$3:$B$502,"Décaissement",'03_FLUX'!$F$3:$F$502,"Réalisé") | F16: =F15+D16-E16+B16-C16 | G16: ='02_PARAMETRES'!B8 | H16: =IF(F16<G16,"ALERTE",IF(F16<G16*1.2,"VIGILANCE","NORMAL"))
A17: =A16+1 | B17: =SUMIFS('03_FLUX'!$E$3:$E$502,'03_FLUX'!$A$3:$A$502,A17,'03_FLUX'!$B$3:$B$502,"Encaissement",'03_FLUX'!$F$3:$F$502,"Prévu") | C17: =SUMIFS('03_FLUX'!$E$3:$E$502,'03_FLUX'!$A$3:$A$502,A17,'03_FLUX'!$B$3:$B$502,"Décaissement",'03_FLUX'!$F$3:$F$502,"Prévu") | D17: =SUMIFS('03_FLUX'!$E$3:$E$502,'03_FLUX'!$A$3:$A$502,A17,'03_FLUX'!$B$3:$B$502,"Encaissement",'03_FLUX'!$F$3:$F$502,"Réalisé") | E17: =SUMIFS('03_FLUX'!$E$3:$E$502,'03_FLUX'!$A$3:$A$502,A17,'03_FLUX'!$B$3:$B$502,"Décaissement",'03_FLUX'!$F$3:$F$502,"Réalisé") | F17: =F16+D17-E17+B17-C17 | G17: ='02_PARAMETRES'!B8 | H17: =IF(F17<G17,"ALERTE",IF(F17<G17*1.2,"VIGILANCE","NORMAL"))
A18: =A17+1 | B18: =SUMIFS('03_FLUX'!$E$3:$E$502,'03_FLUX'!$A$3:$A$502,A18,'03_FLUX'!$B$3:$B$502,"Encaissement",'03_FLUX'!$F$3:$F$502,"Prévu") | C18: =SUMIFS('03_FLUX'!$E$3:$E$502,'03_FLUX'!$A$3:$A$502,A18,'03_FLUX'!$B$3:$B$502,"Décaissement",'03_FLUX'!$F$3:$F$502,"Prévu") | D18: =SUMIFS('03_FLUX'!$E$3:$E$502,'03_FLUX'!$A$3:$A$502,A18,'03_FLUX'!$B$3:$B$502,"Encaissement",'03_FLUX'!$F$3:$F$502,"Réalisé") | E18: =SUMIFS('03_FLUX'!$E$3:$E$502,'03_FLUX'!$A$3:$A$502,A18,'03_FLUX'!$B$3:$B$502,"Décaissement",'03_FLUX'!$F$3:$F$502,"Réalisé") | F18: =F17+D18-E18+B18-C18 | G18: ='02_PARAMETRES'!B8 | H18: =IF(F18<G18,"ALERTE",IF(F18<G18*1.2,"VIGILANCE","NORMAL"))
A19: =A18+1 | B19: =SUMIFS('03_FLUX'!$E$3:$E$502,'03_FLUX'!$A$3:$A$502,A19,'03_FLUX'!$B$3:$B$502,"Encaissement",'03_FLUX'!$F$3:$F$502,"Prévu") | C19: =SUMIFS('03_FLUX'!$E$3:$E$502,'03_FLUX'!$A$3:$A$502,A19,'03_FLUX'!$B$3:$B$502,"Décaissement",'03_FLUX'!$F$3:$F$502,"Prévu") | D19: =SUMIFS('03_FLUX'!$E$3:$E$502,'03_FLUX'!$A$3:$A$502,A19,'03_FLUX'!$B$3:$B$502,"Encaissement",'03_FLUX'!$F$3:$F$502,"Réalisé") | E19: =SUMIFS('03_FLUX'!$E$3:$E$502,'03_FLUX'!$A$3:$A$502,A19,'03_FLUX'!$B$3:$B$502,"Décaissement",'03_FLUX'!$F$3:$F$502,"Réalisé") | F19: =F18+D19-E19+B19-C19 | G19: ='02_PARAMETRES'!B8 | H19: =IF(F19<G19,"ALERTE",IF(F19<G19*1.2,"VIGILANCE","NORMAL"))
A20: =A19+1 | B20: =SUMIFS('03_FLUX'!$E$3:$E$502,'03_FLUX'!$A$3:$A$502,A20,'03_FLUX'!$B$3:$B$502,"Encaissement",'03_FLUX'!$F$3:$F$502,"Prévu") | C20: =SUMIFS('03_FLUX'!$E$3:$E$502,'03_FLUX'!$A$3:$A$502,A20,'03_FLUX'!$B$3:$B$502,"Décaissement",'03_FLUX'!$F$3:$F$502,"Prévu") | D20: =SUMIFS('03_FLUX'!$E$3:$E$502,'03_FLUX'!$A$3:$A$502,A20,'03_FLUX'!$B$3:$B$502,"Encaissement",'03_FLUX'!$F$3:$F$502,"Réalisé") | E20: =SUMIFS('03_FLUX'!$E$3:$E$502,'03_FLUX'!$A$3:$A$502,A20,'03_FLUX'!$B$3:$B$502,"Décaissement",'03_FLUX'!$F$3:$F$502,"Réalisé") | F20: =F19+D20-E20+B20-C20 | G20: ='02_PARAMETRES'!B8 | H20: =IF(F20<G20,"ALERTE",IF(F20<G20*1.2,"VIGILANCE","NORMAL"))
A21: =A20+1 | B21: =SUMIFS('03_FLUX'!$E$3:$E$502,'03_FLUX'!$A$3:$A$502,A21,'03_FLUX'!$B$3:$B$502,"Encaissement",'03_FLUX'!$F$3:$F$502,"Prévu") | C21: =SUMIFS('03_FLUX'!$E$3:$E$502,'03_FLUX'!$A$3:$A$502,A21,'03_FLUX'!$B$3:$B$502,"Décaissement",'03_FLUX'!$F$3:$F$502,"Prévu") | D21: =SUMIFS('03_FLUX'!$E$3:$E$502,'03_FLUX'!$A$3:$A$502,A21,'03_FLUX'!$B$3:$B$502,"Encaissement",'03_FLUX'!$F$3:$F$502,"Réalisé") | E21: =SUMIFS('03_FLUX'!$E$3:$E$502,'03_FLUX'!$A$3:$A$502,A21,'03_FLUX'!$B$3:$B$502,"Décaissement",'03_FLUX'!$F$3:$F$502,"Réalisé") | F21: =F20+D21-E21+B21-C21 | G21: ='02_PARAMETRES'!B8 | H21: =IF(F21<G21,"ALERTE",IF(F21<G21*1.2,"VIGILANCE","NORMAL"))
A22: =A21+1 | B22: =SUMIFS('03_FLUX'!$E$3:$E$502,'03_FLUX'!$A$3:$A$502,A22,'03_FLUX'!$B$3:$B$502,"Encaissement",'03_FLUX'!$F$3:$F$502,"Prévu") | C22: =SUMIFS('03_FLUX'!$E$3:$E$502,'03_FLUX'!$A$3:$A$502,A22,'03_FLUX'!$B$3:$B$502,"Décaissement",'03_FLUX'!$F$3:$F$502,"Prévu") | D22: =SUMIFS('03_FLUX'!$E$3:$E$502,'03_FLUX'!$A$3:$A$502,A22,'03_FLUX'!$B$3:$B$502,"Encaissement",'03_FLUX'!$F$3:$F$502,"Réalisé") | E22: =SUMIFS('03_FLUX'!$E$3:$E$502,'03_FLUX'!$A$3:$A$502,A22,'03_FLUX'!$B$3:$B$502,"Décaissement",'03_FLUX'!$F$3:$F$502,"Réalisé") | F22: =F21+D22-E22+B22-C22 | G22: ='02_PARAMETRES'!B8 | H22: =IF(F22<G22,"ALERTE",IF(F22<G22*1.2,"VIGILANCE","NORMAL"))
A23: =A22+1 | B23: =SUMIFS('03_FLUX'!$E$3:$E$502,'03_FLUX'!$A$3:$A$502,A23,'03_FLUX'!$B$3:$B$502,"Encaissement",'03_FLUX'!$F$3:$F$502,"Prévu") | C23: =SUMIFS('03_FLUX'!$E$3:$E$502,'03_FLUX'!$A$3:$A$502,A23,'03_FLUX'!$B$3:$B$502,"Décaissement",'03_FLUX'!$F$3:$F$502,"Prévu") | D23: =SUMIFS('03_FLUX'!$E$3:$E$502,'03_FLUX'!$A$3:$A$502,A23,'03_FLUX'!$B$3:$B$502,"Encaissement",'03_FLUX'!$F$3:$F$502,"Réalisé") | E23: =SUMIFS('03_FLUX'!$E$3:$E$502,'03_FLUX'!$A$3:$A$502,A23,'03_FLUX'!$B$3:$B$502,"Décaissement",'03_FLUX'!$F$3:$F$502,"Réalisé") | F23: =F22+D23-E23+B23-C23 | G23: ='02_PARAMETRES'!B8 | H23: =IF(F23<G23,"ALERTE",IF(F23<G23*1.2,"VIGILANCE","NORMAL"))
A24: =A23+1 | B24: =SUMIFS('03_FLUX'!$E$3:$E$502,'03_FLUX'!$A$3:$A$502,A24,'03_FLUX'!$B$3:$B$502,"Encaissement",'03_FLUX'!$F$3:$F$502,"Prévu") | C24: =SUMIFS('03_FLUX'!$E$3:$E$502,'03_FLUX'!$A$3:$A$502,A24,'03_FLUX'!$B$3:$B$502,"Décaissement",'03_FLUX'!$F$3:$F$502,"Prévu") | D24: =SUMIFS('03_FLUX'!$E$3:$E$502,'03_FLUX'!$A$3:$A$502,A24,'03_FLUX'!$B$3:$B$502,"Encaissement",'03_FLUX'!$F$3:$F$502,"Réalisé") | E24: =SUMIFS('03_FLUX'!$E$3:$E$502,'03_FLUX'!$A$3:$A$502,A24,'03_FLUX'!$B$3:$B$502,"Décaissement",'03_FLUX'!$F$3:$F$502,"Réalisé") | F24: =F23+D24-E24+B24-C24 | G24: ='02_PARAMETRES'!B8 | H24: =IF(F24<G24,"ALERTE",IF(F24<G24*1.2,"VIGILANCE","NORMAL"))
A25: =A24+1 | B25: =SUMIFS('03_FLUX'!$E$3:$E$502,'03_FLUX'!$A$3:$A$502,A25,'03_FLUX'!$B$3:$B$502,"Encaissement",'03_FLUX'!$F$3:$F$502,"Prévu") | C25: =SUMIFS('03_FLUX'!$E$3:$E$502,'03_FLUX'!$A$3:$A$502,A25,'03_FLUX'!$B$3:$B$502,"Décaissement",'03_FLUX'!$F$3:$F$502,"Prévu") | D25: =SUMIFS('03_FLUX'!$E$3:$E$502,'03_FLUX'!$A$3:$A$502,A25,'03_FLUX'!$B$3:$B$502,"Encaissement",'03_FLUX'!$F$3:$F$502,"Réalisé") | E25: =SUMIFS('03_FLUX'!$E$3:$E$502,'03_FLUX'!$A$3:$A$502,A25,'03_FLUX'!$B$3:$B$502,"Décaissement",'03_FLUX'!$F$3:$F$502,"Réalisé") | F25: =F24+D25-E25+B25-C25 | G25: ='02_PARAMETRES'!B8 | H25: =IF(F25<G25,"ALERTE",IF(F25<G25*1.2,"VIGILANCE","NORMAL"))
A26: =A25+1 | B26: =SUMIFS('03_FLUX'!$E$3:$E$502,'03_FLUX'!$A$3:$A$502,A26,'03_FLUX'!$B$3:$B$502,"Encaissement",'03_FLUX'!$F$3:$F$502,"Prévu") | C26: =SUMIFS('03_FLUX'!$E$3:$E$502,'03_FLUX'!$A$3:$A$502,A26,'03_FLUX'!$B$3:$B$502,"Décaissement",'03_FLUX'!$F$3:$F$502,"Prévu") | D26: =SUMIFS('03_FLUX'!$E$3:$E$502,'03_FLUX'!$A$3:$A$502,A26,'03_FLUX'!$B$3:$B$502,"Encaissement",'03_FLUX'!$F$3:$F$502,"Réalisé") | E26: =SUMIFS('03_FLUX'!$E$3:$E$502,'03_FLUX'!$A$3:$A$502,A26,'03_FLUX'!$B$3:$B$502,"Décaissement",'03_FLUX'!$F$3:$F$502,"Réalisé") | F26: =F25+D26-E26+B26-C26 | G26: ='02_PARAMETRES'!B8 | H26: =IF(F26<G26,"ALERTE",IF(F26<G26*1.2,"VIGILANCE","NORMAL"))
A27: =A26+1 | B27: =SUMIFS('03_FLUX'!$E$3:$E$502,'03_FLUX'!$A$3:$A$502,A27,'03_FLUX'!$B$3:$B$502,"Encaissement",'03_FLUX'!$F$3:$F$502,"Prévu") | C27: =SUMIFS('03_FLUX'!$E$3:$E$502,'03_FLUX'!$A$3:$A$502,A27,'03_FLUX'!$B$3:$B$502,"Décaissement",'03_FLUX'!$F$3:$F$502,"Prévu") | D27: =SUMIFS('03_FLUX'!$E$3:$E$502,'03_FLUX'!$A$3:$A$502,A27,'03_FLUX'!$B$3:$B$502,"Encaissement",'03_FLUX'!$F$3:$F$502,"Réalisé") | E27: =SUMIFS('03_FLUX'!$E$3:$E$502,'03_FLUX'!$A$3:$A$502,A27,'03_FLUX'!$B$3:$B$502,"Décaissement",'03_FLUX'!$F$3:$F$502,"Réalisé") | F27: =F26+D27-E27+B27-C27 | G27: ='02_PARAMETRES'!B8 | H27: =IF(F27<G27,"ALERTE",IF(F27<G27*1.2,"VIGILANCE","NORMAL"))
A28: =A27+1 | B28: =SUMIFS('03_FLUX'!$E$3:$E$502,'03_FLUX'!$A$3:$A$502,A28,'03_FLUX'!$B$3:$B$502,"Encaissement",'03_FLUX'!$F$3:$F$502,"Prévu") | C28: =SUMIFS('03_FLUX'!$E$3:$E$502,'03_FLUX'!$A$3:$A$502,A28,'03_FLUX'!$B$3:$B$502,"Décaissement",'03_FLUX'!$F$3:$F$502,"Prévu") | D28: =SUMIFS('03_FLUX'!$E$3:$E$502,'03_FLUX'!$A$3:$A$502,A28,'03_FLUX'!$B$3:$B$502,"Encaissement",'03_FLUX'!$F$3:$F$502,"Réalisé") | E28: =SUMIFS('03_FLUX'!$E$3:$E$502,'03_FLUX'!$A$3:$A$502,A28,'03_FLUX'!$B$3:$B$502,"Décaissement",'03_FLUX'!$F$3:$F$502,"Réalisé") | F28: =F27+D28-E28+B28-C28 | G28: ='02_PARAMETRES'!B8 | H28: =IF(F28<G28,"ALERTE",IF(F28<G28*1.2,"VIGILANCE","NORMAL"))
A29: =A28+1 | B29: =SUMIFS('03_FLUX'!$E$3:$E$502,'03_FLUX'!$A$3:$A$502,A29,'03_FLUX'!$B$3:$B$502,"Encaissement",'03_FLUX'!$F$3:$F$502,"Prévu") | C29: =SUMIFS('03_FLUX'!$E$3:$E$502,'03_FLUX'!$A$3:$A$502,A29,'03_FLUX'!$B$3:$B$502,"Décaissement",'03_FLUX'!$F$3:$F$502,"Prévu") | D29: =SUMIFS('03_FLUX'!$E$3:$E$502,'03_FLUX'!$A$3:$A$502,A29,'03_FLUX'!$B$3:$B$502,"Encaissement",'03_FLUX'!$F$3:$F$502,"Réalisé") | E29: =SUMIFS('03_FLUX'!$E$3:$E$502,'03_FLUX'!$A$3:$A$502,A29,'03_FLUX'!$B$3:$B$502,"Décaissement",'03_FLUX'!$F$3:$F$502,"Réalisé") | F29: =F28+D29-E29+B29-C29 | G29: ='02_PARAMETRES'!B8 | H29: =IF(F29<G29,"ALERTE",IF(F29<G29*1.2,"VIGILANCE","NORMAL"))
A30: =A29+1 | B30: =SUMIFS('03_FLUX'!$E$3:$E$502,'03_FLUX'!$A$3:$A$502,A30,'03_FLUX'!$B$3:$B$502,"Encaissement",'03_FLUX'!$F$3:$F$502,"Prévu") | C30: =SUMIFS('03_FLUX'!$E$3:$E$502,'03_FLUX'!$A$3:$A$502,A30,'03_FLUX'!$B$3:$B$502,"Décaissement",'03_FLUX'!$F$3:$F$502,"Prévu") | D30: =SUMIFS('03_FLUX'!$E$3:$E$502,'03_FLUX'!$A$3:$A$502,A30,'03_FLUX'!$B$3:$B$502,"Encaissement",'03_FLUX'!$F$3:$F$502,"Réalisé") | E30: =SUMIFS('03_FLUX'!$E$3:$E$502,'03_FLUX'!$A$3:$A$502,A30,'03_FLUX'!$B$3:$B$502,"Décaissement",'03_FLUX'!$F$3:$F$502,"Réalisé") | F30: =F29+D30-E30+B30-C30 | G30: ='02_PARAMETRES'!B8 | H30: =IF(F30<G30,"ALERTE",IF(F30<G30*1.2,"VIGILANCE","NORMAL"))
A31: =A30+1 | B31: =SUMIFS('03_FLUX'!$E$3:$E$502,'03_FLUX'!$A$3:$A$502,A31,'03_FLUX'!$B$3:$B$502,"Encaissement",'03_FLUX'!$F$3:$F$502,"Prévu") | C31: =SUMIFS('03_FLUX'!$E$3:$E$502,'03_FLUX'!$A$3:$A$502,A31,'03_FLUX'!$B$3:$B$502,"Décaissement",'03_FLUX'!$F$3:$F$502,"Prévu") | D31: =SUMIFS('03_FLUX'!$E$3:$E$502,'03_FLUX'!$A$3:$A$502,A31,'03_FLUX'!$B$3:$B$502,"Encaissement",'03_FLUX'!$F$3:$F$502,"Réalisé") | E31: =SUMIFS('03_FLUX'!$E$3:$E$502,'03_FLUX'!$A$3:$A$502,A31,'03_FLUX'!$B$3:$B$502,"Décaissement",'03_FLUX'!$F$3:$F$502,"Réalisé") | F31: =F30+D31-E31+B31-C31 | G31: ='02_PARAMETRES'!B8 | H31: =IF(F31<G31,"ALERTE",IF(F31<G31*1.2,"VIGILANCE","NORMAL"))
A32: =A31+1 | B32: =SUMIFS('03_FLUX'!$E$3:$E$502,'03_FLUX'!$A$3:$A$502,A32,'03_FLUX'!$B$3:$B$502,"Encaissement",'03_FLUX'!$F$3:$F$502,"Prévu") | C32: =SUMIFS('03_FLUX'!$E$3:$E$502,'03_FLUX'!$A$3:$A$502,A32,'03_FLUX'!$B$3:$B$502,"Décaissement",'03_FLUX'!$F$3:$F$502,"Prévu") | D32: =SUMIFS('03_FLUX'!$E$3:$E$502,'03_FLUX'!$A$3:$A$502,A32,'03_FLUX'!$B$3:$B$502,"Encaissement",'03_FLUX'!$F$3:$F$502,"Réalisé") | E32: =SUMIFS('03_FLUX'!$E$3:$E$502,'03_FLUX'!$A$3:$A$502,A32,'03_FLUX'!$B$3:$B$502,"Décaissement",'03_FLUX'!$F$3:$F$502,"Réalisé") | F32: =F31+D32-E32+B32-C32 | G32: ='02_PARAMETRES'!B8 | H32: =IF(F32<G32,"ALERTE",IF(F32<G32*1.2,"VIGILANCE","NORMAL"))
A33: =A32+1 | B33: =SUMIFS('03_FLUX'!$E$3:$E$502,'03_FLUX'!$A$3:$A$502,A33,'03_FLUX'!$B$3:$B$502,"Encaissement",'03_FLUX'!$F$3:$F$502,"Prévu") | C33: =SUMIFS('03_FLUX'!$E$3:$E$502,'03_FLUX'!$A$3:$A$502,A33,'03_FLUX'!$B$3:$B$502,"Décaissement",'03_FLUX'!$F$3:$F$502,"Prévu") | D33: =SUMIFS('03_FLUX'!$E$3:$E$502,'03_FLUX'!$A$3:$A$502,A33,'03_FLUX'!$B$3:$B$502,"Encaissement",'03_FLUX'!$F$3:$F$502,"Réalisé") | E33: =SUMIFS('03_FLUX'!$E$3:$E$502,'03_FLUX'!$A$3:$A$502,A33,'03_FLUX'!$B$3:$B$502,"Décaissement",'03_FLUX'!$F$3:$F$502,"Réalisé") | F33: =F32+D33-E33+B33-C33 | G33: ='02_PARAMETRES'!B8 | H33: =IF(F33<G33,"ALERTE",IF(F33<G33*1.2,"VIGILANCE","NORMAL"))
A34: =A33+1 | B34: =SUMIFS('03_FLUX'!$E$3:$E$502,'03_FLUX'!$A$3:$A$502,A34,'03_FLUX'!$B$3:$B$502,"Encaissement",'03_FLUX'!$F$3:$F$502,"Prévu") | C34: =SUMIFS('03_FLUX'!$E$3:$E$502,'03_FLUX'!$A$3:$A$502,A34,'03_FLUX'!$B$3:$B$502,"Décaissement",'03_FLUX'!$F$3:$F$502,"Prévu") | D34: =SUMIFS('03_FLUX'!$E$3:$E$502,'03_FLUX'!$A$3:$A$502,A34,'03_FLUX'!$B$3:$B$502,"Encaissement",'03_FLUX'!$F$3:$F$502,"Réalisé") | E34: =SUMIFS('03_FLUX'!$E$3:$E$502,'03_FLUX'!$A$3:$A$502,A34,'03_FLUX'!$B$3:$B$502,"Décaissement",'03_FLUX'!$F$3:$F$502,"Réalisé") | F34: =F33+D34-E34+B34-C34 | G34: ='02_PARAMETRES'!B8 | H34: =IF(F34<G34,"ALERTE",IF(F34<G34*1.2,"VIGILANCE","NORMAL"))
A35: =A34+1 | B35: =SUMIFS('03_FLUX'!$E$3:$E$502,'03_FLUX'!$A$3:$A$502,A35,'03_FLUX'!$B$3:$B$502,"Encaissement",'03_FLUX'!$F$3:$F$502,"Prévu") | C35: =SUMIFS('03_FLUX'!$E$3:$E$502,'03_FLUX'!$A$3:$A$502,A35,'03_FLUX'!$B$3:$B$502,"Décaissement",'03_FLUX'!$F$3:$F$502,"Prévu") | D35: =SUMIFS('03_FLUX'!$E$3:$E$502,'03_FLUX'!$A$3:$A$502,A35,'03_FLUX'!$B$3:$B$502,"Encaissement",'03_FLUX'!$F$3:$F$502,"Réalisé") | E35: =SUMIFS('03_FLUX'!$E$3:$E$502,'03_FLUX'!$A$3:$A$502,A35,'03_FLUX'!$B$3:$B$502,"Décaissement",'03_FLUX'!$F$3:$F$502,"Réalisé") | F35: =F34+D35-E35+B35-C35 | G35: ='02_PARAMETRES'!B8 | H35: =IF(F35<G35,"ALERTE",IF(F35<G35*1.2,"VIGILANCE","NORMAL"))
A36: =A35+1 | B36: =SUMIFS('03_FLUX'!$E$3:$E$502,'03_FLUX'!$A$3:$A$502,A36,'03_FLUX'!$B$3:$B$502,"Encaissement",'03_FLUX'!$F$3:$F$502,"Prévu") | C36: =SUMIFS('03_FLUX'!$E$3:$E$502,'03_FLUX'!$A$3:$A$502,A36,'03_FLUX'!$B$3:$B$502,"Décaissement",'03_FLUX'!$F$3:$F$502,"Prévu") | D36: =SUMIFS('03_FLUX'!$E$3:$E$502,'03_FLUX'!$A$3:$A$502,A36,'03_FLUX'!$B$3:$B$502,"Encaissement",'03_FLUX'!$F$3:$F$502,"Réalisé") | E36: =SUMIFS('03_FLUX'!$E$3:$E$502,'03_FLUX'!$A$3:$A$502,A36,'03_FLUX'!$B$3:$B$502,"Décaissement",'03_FLUX'!$F$3:$F$502,"Réalisé") | F36: =F35+D36-E36+B36-C36 | G36: ='02_PARAMETRES'!B8 | H36: =IF(F36<G36,"ALERTE",IF(F36<G36*1.2,"VIGILANCE","NORMAL"))
A37: =A36+1 | B37: =SUMIFS('03_FLUX'!$E$3:$E$502,'03_FLUX'!$A$3:$A$502,A37,'03_FLUX'!$B$3:$B$502,"Encaissement",'03_FLUX'!$F$3:$F$502,"Prévu") | C37: =SUMIFS('03_FLUX'!$E$3:$E$502,'03_FLUX'!$A$3:$A$502,A37,'03_FLUX'!$B$3:$B$502,"Décaissement",'03_FLUX'!$F$3:$F$502,"Prévu") | D37: =SUMIFS('03_FLUX'!$E$3:$E$502,'03_FLUX'!$A$3:$A$502,A37,'03_FLUX'!$B$3:$B$502,"Encaissement",'03_FLUX'!$F$3:$F$502,"Réalisé") | E37: =SUMIFS('03_FLUX'!$E$3:$E$502,'03_FLUX'!$A$3:$A$502,A37,'03_FLUX'!$B$3:$B$502,"Décaissement",'03_FLUX'!$F$3:$F$502,"Réalisé") | F37: =F36+D37-E37+B37-C37 | G37: ='02_PARAMETRES'!B8 | H37: =IF(F37<G37,"ALERTE",IF(F37<G37*1.2,"VIGILANCE","NORMAL"))
A38: =A37+1 | B38: =SUMIFS('03_FLUX'!$E$3:$E$502,'03_FLUX'!$A$3:$A$502,A38,'03_FLUX'!$B$3:$B$502,"Encaissement",'03_FLUX'!$F$3:$F$502,"Prévu") | C38: =SUMIFS('03_FLUX'!$E$3:$E$502,'03_FLUX'!$A$3:$A$502,A38,'03_FLUX'!$B$3:$B$502,"Décaissement",'03_FLUX'!$F$3:$F$502,"Prévu") | D38: =SUMIFS('03_FLUX'!$E$3:$E$502,'03_FLUX'!$A$3:$A$502,A38,'03_FLUX'!$B$3:$B$502,"Encaissement",'03_FLUX'!$F$3:$F$502,"Réalisé") | E38: =SUMIFS('03_FLUX'!$E$3:$E$502,'03_FLUX'!$A$3:$A$502,A38,'03_FLUX'!$B$3:$B$502,"Décaissement",'03_FLUX'!$F$3:$F$502,"Réalisé") | F38: =F37+D38-E38+B38-C38 | G38: ='02_PARAMETRES'!B8 | H38: =IF(F38<G38,"ALERTE",IF(F38<G38*1.2,"VIGILANCE","NORMAL"))
A39: =A38+1 | B39: =SUMIFS('03_FLUX'!$E$3:$E$502,'03_FLUX'!$A$3:$A$502,A39,'03_FLUX'!$B$3:$B$502,"Encaissement",'03_FLUX'!$F$3:$F$502,"Prévu") | C39: =SUMIFS('03_FLUX'!$E$3:$E$502,'03_FLUX'!$A$3:$A$502,A39,'03_FLUX'!$B$3:$B$502,"Décaissement",'03_FLUX'!$F$3:$F$502,"Prévu") | D39: =SUMIFS('03_FLUX'!$E$3:$E$502,'03_FLUX'!$A$3:$A$502,A39,'03_FLUX'!$B$3:$B$502,"Encaissement",'03_FLUX'!$F$3:$F$502,"Réalisé") | E39: =SUMIFS('03_FLUX'!$E$3:$E$502,'03_FLUX'!$A$3:$A$502,A39,'03_FLUX'!$B$3:$B$502,"Décaissement",'03_FLUX'!$F$3:$F$502,"Réalisé") | F39: =F38+D39-E39+B39-C39 | G39: ='02_PARAMETRES'!B8 | H39: =IF(F39<G39,"ALERTE",IF(F39<G39*1.2,"VIGILANCE","NORMAL"))
A40: =A39+1 | B40: =SUMIFS('03_FLUX'!$E$3:$E$502,'03_FLUX'!$A$3:$A$502,A40,'03_FLUX'!$B$3:$B$502,"Encaissement",'03_FLUX'!$F$3:$F$502,"Prévu") | C40: =SUMIFS('03_FLUX'!$E$3:$E$502,'03_FLUX'!$A$3:$A$502,A40,'03_FLUX'!$B$3:$B$502,"Décaissement",'03_FLUX'!$F$3:$F$502,"Prévu") | D40: =SUMIFS('03_FLUX'!$E$3:$E$502,'03_FLUX'!$A$3:$A$502,A40,'03_FLUX'!$B$3:$B$502,"Encaissement",'03_FLUX'!$F$3:$F$502,"Réalisé") | E40: =SUMIFS('03_FLUX'!$E$3:$E$502,'03_FLUX'!$A$3:$A$502,A40,'03_FLUX'!$B$3:$B$502,"Décaissement",'03_FLUX'!$F$3:$F$502,"Réalisé") | F40: =F39+D40-E40+B40-C40 | G40: ='02_PARAMETRES'!B8 | H40: =IF(F40<G40,"ALERTE",IF(F40<G40*1.2,"VIGILANCE","NORMAL"))
A41: =A40+1 | B41: =SUMIFS('03_FLUX'!$E$3:$E$502,'03_FLUX'!$A$3:$A$502,A41,'03_FLUX'!$B$3:$B$502,"Encaissement",'03_FLUX'!$F$3:$F$502,"Prévu") | C41: =SUMIFS('03_FLUX'!$E$3:$E$502,'03_FLUX'!$A$3:$A$502,A41,'03_FLUX'!$B$3:$B$502,"Décaissement",'03_FLUX'!$F$3:$F$502,"Prévu") | D41: =SUMIFS('03_FLUX'!$E$3:$E$502,'03_FLUX'!$A$3:$A$502,A41,'03_FLUX'!$B$3:$B$502,"Encaissement",'03_FLUX'!$F$3:$F$502,"Réalisé") | E41: =SUMIFS('03_FLUX'!$E$3:$E$502,'03_FLUX'!$A$3:$A$502,A41,'03_FLUX'!$B$3:$B$502,"Décaissement",'03_FLUX'!$F$3:$F$502,"Réalisé") | F41: =F40+D41-E41+B41-C41 | G41: ='02_PARAMETRES'!B8 | H41: =IF(F41<G41,"ALERTE",IF(F41<G41*1.2,"VIGILANCE","NORMAL"))
A42: =A41+1 | B42: =SUMIFS('03_FLUX'!$E$3:$E$502,'03_FLUX'!$A$3:$A$502,A42,'03_FLUX'!$B$3:$B$502,"Encaissement",'03_FLUX'!$F$3:$F$502,"Prévu") | C42: =SUMIFS('03_FLUX'!$E$3:$E$502,'03_FLUX'!$A$3:$A$502,A42,'03_FLUX'!$B$3:$B$502,"Décaissement",'03_FLUX'!$F$3:$F$502,"Prévu") | D42: =SUMIFS('03_FLUX'!$E$3:$E$502,'03_FLUX'!$A$3:$A$502,A42,'03_FLUX'!$B$3:$B$502,"Encaissement",'03_FLUX'!$F$3:$F$502,"Réalisé") | E42: =SUMIFS('03_FLUX'!$E$3:$E$502,'03_FLUX'!$A$3:$A$502,A42,'03_FLUX'!$B$3:$B$502,"Décaissement",'03_FLUX'!$F$3:$F$502,"Réalisé") | F42: =F41+D42-E42+B42-C42 | G42: ='02_PARAMETRES'!B8 | H42: =IF(F42<G42,"ALERTE",IF(F42<G42*1.2,"VIGILANCE","NORMAL"))
A43: =A42+1 | B43: =SUMIFS('03_FLUX'!$E$3:$E$502,'03_FLUX'!$A$3:$A$502,A43,'03_FLUX'!$B$3:$B$502,"Encaissement",'03_FLUX'!$F$3:$F$502,"Prévu") | C43: =SUMIFS('03_FLUX'!$E$3:$E$502,'03_FLUX'!$A$3:$A$502,A43,'03_FLUX'!$B$3:$B$502,"Décaissement",'03_FLUX'!$F$3:$F$502,"Prévu") | D43: =SUMIFS('03_FLUX'!$E$3:$E$502,'03_FLUX'!$A$3:$A$502,A43,'03_FLUX'!$B$3:$B$502,"Encaissement",'03_FLUX'!$F$3:$F$502,"Réalisé") | E43: =SUMIFS('03_FLUX'!$E$3:$E$502,'03_FLUX'!$A$3:$A$502,A43,'03_FLUX'!$B$3:$B$502,"Décaissement",'03_FLUX'!$F$3:$F$502,"Réalisé") | F43: =F42+D43-E43+B43-C43 | G43: ='02_PARAMETRES'!B8 | H43: =IF(F43<G43,"ALERTE",IF(F43<G43*1.2,"VIGILANCE","NORMAL"))
A44: =A43+1 | B44: =SUMIFS('03_FLUX'!$E$3:$E$502,'03_FLUX'!$A$3:$A$502,A44,'03_FLUX'!$B$3:$B$502,"Encaissement",'03_FLUX'!$F$3:$F$502,"Prévu") | C44: =SUMIFS('03_FLUX'!$E$3:$E$502,'03_FLUX'!$A$3:$A$502,A44,'03_FLUX'!$B$3:$B$502,"Décaissement",'03_FLUX'!$F$3:$F$502,"Prévu") | D44: =SUMIFS('03_FLUX'!$E$3:$E$502,'03_FLUX'!$A$3:$A$502,A44,'03_FLUX'!$B$3:$B$502,"Encaissement",'03_FLUX'!$F$3:$F$502,"Réalisé") | E44: =SUMIFS('03_FLUX'!$E$3:$E$502,'03_FLUX'!$A$3:$A$502,A44,'03_FLUX'!$B$3:$B$502,"Décaissement",'03_FLUX'!$F$3:$F$502,"Réalisé") | F44: =F43+D44-E44+B44-C44 | G44: ='02_PARAMETRES'!B8 | H44: =IF(F44<G44,"ALERTE",IF(F44<G44*1.2,"VIGILANCE","NORMAL"))
A45: =A44+1 | B45: =SUMIFS('03_FLUX'!$E$3:$E$502,'03_FLUX'!$A$3:$A$502,A45,'03_FLUX'!$B$3:$B$502,"Encaissement",'03_FLUX'!$F$3:$F$502,"Prévu") | C45: =SUMIFS('03_FLUX'!$E$3:$E$502,'03_FLUX'!$A$3:$A$502,A45,'03_FLUX'!$B$3:$B$502,"Décaissement",'03_FLUX'!$F$3:$F$502,"Prévu") | D45: =SUMIFS('03_FLUX'!$E$3:$E$502,'03_FLUX'!$A$3:$A$502,A45,'03_FLUX'!$B$3:$B$502,"Encaissement",'03_FLUX'!$F$3:$F$502,"Réalisé") | E45: =SUMIFS('03_FLUX'!$E$3:$E$502,'03_FLUX'!$A$3:$A$502,A45,'03_FLUX'!$B$3:$B$502,"Décaissement",'03_FLUX'!$F$3:$F$502,"Réalisé") | F45: =F44+D45-E45+B45-C45 | G45: ='02_PARAMETRES'!B8 | H45: =IF(F45<G45,"ALERTE",IF(F45<G45*1.2,"VIGILANCE","NORMAL"))
A46: =A45+1 | B46: =SUMIFS('03_FLUX'!$E$3:$E$502,'03_FLUX'!$A$3:$A$502,A46,'03_FLUX'!$B$3:$B$502,"Encaissement",'03_FLUX'!$F$3:$F$502,"Prévu") | C46: =SUMIFS('03_FLUX'!$E$3:$E$502,'03_FLUX'!$A$3:$A$502,A46,'03_FLUX'!$B$3:$B$502,"Décaissement",'03_FLUX'!$F$3:$F$502,"Prévu") | D46: =SUMIFS('03_FLUX'!$E$3:$E$502,'03_FLUX'!$A$3:$A$502,A46,'03_FLUX'!$B$3:$B$502,"Encaissement",'03_FLUX'!$F$3:$F$502,"Réalisé") | E46: =SUMIFS('03_FLUX'!$E$3:$E$502,'03_FLUX'!$A$3:$A$502,A46,'03_FLUX'!$B$3:$B$502,"Décaissement",'03_FLUX'!$F$3:$F$502,"Réalisé") | F46: =F45+D46-E46+B46-C46 | G46: ='02_PARAMETRES'!B8 | H46: =IF(F46<G46,"ALERTE",IF(F46<G46*1.2,"VIGILANCE","NORMAL"))
A47: =A46+1 | B47: =SUMIFS('03_FLUX'!$E$3:$E$502,'03_FLUX'!$A$3:$A$502,A47,'03_FLUX'!$B$3:$B$502,"Encaissement",'03_FLUX'!$F$3:$F$502,"Prévu") | C47: =SUMIFS('03_FLUX'!$E$3:$E$502,'03_FLUX'!$A$3:$A$502,A47,'03_FLUX'!$B$3:$B$502,"Décaissement",'03_FLUX'!$F$3:$F$502,"Prévu") | D47: =SUMIFS('03_FLUX'!$E$3:$E$502,'03_FLUX'!$A$3:$A$502,A47,'03_FLUX'!$B$3:$B$502,"Encaissement",'03_FLUX'!$F$3:$F$502,"Réalisé") | E47: =SUMIFS('03_FLUX'!$E$3:$E$502,'03_FLUX'!$A$3:$A$502,A47,'03_FLUX'!$B$3:$B$502,"Décaissement",'03_FLUX'!$F$3:$F$502,"Réalisé") | F47: =F46+D47-E47+B47-C47 | G47: ='02_PARAMETRES'!B8 | H47: =IF(F47<G47,"ALERTE",IF(F47<G47*1.2,"VIGILANCE","NORMAL"))
A48: =A47+1 | B48: =SUMIFS('03_FLUX'!$E$3:$E$502,'03_FLUX'!$A$3:$A$502,A48,'03_FLUX'!$B$3:$B$502,"Encaissement",'03_FLUX'!$F$3:$F$502,"Prévu") | C48: =SUMIFS('03_FLUX'!$E$3:$E$502,'03_FLUX'!$A$3:$A$502,A48,'03_FLUX'!$B$3:$B$502,"Décaissement",'03_FLUX'!$F$3:$F$502,"Prévu") | D48: =SUMIFS('03_FLUX'!$E$3:$E$502,'03_FLUX'!$A$3:$A$502,A48,'03_FLUX'!$B$3:$B$502,"Encaissement",'03_FLUX'!$F$3:$F$502,"Réalisé") | E48: =SUMIFS('03_FLUX'!$E$3:$E$502,'03_FLUX'!$A$3:$A$502,A48,'03_FLUX'!$B$3:$B$502,"Décaissement",'03_FLUX'!$F$3:$F$502,"Réalisé") | F48: =F47+D48-E48+B48-C48 | G48: ='02_PARAMETRES'!B8 | H48: =IF(F48<G48,"ALERTE",IF(F48<G48*1.2,"VIGILANCE","NORMAL"))
A49: =A48+1 | B49: =SUMIFS('03_FLUX'!$E$3:$E$502,'03_FLUX'!$A$3:$A$502,A49,'03_FLUX'!$B$3:$B$502,"Encaissement",'03_FLUX'!$F$3:$F$502,"Prévu") | C49: =SUMIFS('03_FLUX'!$E$3:$E$502,'03_FLUX'!$A$3:$A$502,A49,'03_FLUX'!$B$3:$B$502,"Décaissement",'03_FLUX'!$F$3:$F$502,"Prévu") | D49: =SUMIFS('03_FLUX'!$E$3:$E$502,'03_FLUX'!$A$3:$A$502,A49,'03_FLUX'!$B$3:$B$502,"Encaissement",'03_FLUX'!$F$3:$F$502,"Réalisé") | E49: =SUMIFS('03_FLUX'!$E$3:$E$502,'03_FLUX'!$A$3:$A$502,A49,'03_FLUX'!$B$3:$B$502,"Décaissement",'03_FLUX'!$F$3:$F$502,"Réalisé") | F49: =F48+D49-E49+B49-C49 | G49: ='02_PARAMETRES'!B8 | H49: =IF(F49<G49,"ALERTE",IF(F49<G49*1.2,"VIGILANCE","NORMAL"))
A50: =A49+1 | B50: =SUMIFS('03_FLUX'!$E$3:$E$502,'03_FLUX'!$A$3:$A$502,A50,'03_FLUX'!$B$3:$B$502,"Encaissement",'03_FLUX'!$F$3:$F$502,"Prévu") | C50: =SUMIFS('03_FLUX'!$E$3:$E$502,'03_FLUX'!$A$3:$A$502,A50,'03_FLUX'!$B$3:$B$502,"Décaissement",'03_FLUX'!$F$3:$F$502,"Prévu") | D50: =SUMIFS('03_FLUX'!$E$3:$E$502,'03_FLUX'!$A$3:$A$502,A50,'03_FLUX'!$B$3:$B$502,"Encaissement",'03_FLUX'!$F$3:$F$502,"Réalisé") | E50: =SUMIFS('03_FLUX'!$E$3:$E$502,'03_FLUX'!$A$3:$A$502,A50,'03_FLUX'!$B$3:$B$502,"Décaissement",'03_FLUX'!$F$3:$F$502,"Réalisé") | F50: =F49+D50-E50+B50-C50 | G50: ='02_PARAMETRES'!B8 | H50: =IF(F50<G50,"ALERTE",IF(F50<G50*1.2,"VIGILANCE","NORMAL"))
A51: =A50+1 | B51: =SUMIFS('03_FLUX'!$E$3:$E$502,'03_FLUX'!$A$3:$A$502,A51,'03_FLUX'!$B$3:$B$502,"Encaissement",'03_FLUX'!$F$3:$F$502,"Prévu") | C51: =SUMIFS('03_FLUX'!$E$3:$E$502,'03_FLUX'!$A$3:$A$502,A51,'03_FLUX'!$B$3:$B$502,"Décaissement",'03_FLUX'!$F$3:$F$502,"Prévu") | D51: =SUMIFS('03_FLUX'!$E$3:$E$502,'03_FLUX'!$A$3:$A$502,A51,'03_FLUX'!$B$3:$B$502,"Encaissement",'03_FLUX'!$F$3:$F$502,"Réalisé") | E51: =SUMIFS('03_FLUX'!$E$3:$E$502,'03_FLUX'!$A$3:$A$502,A51,'03_FLUX'!$B$3:$B$502,"Décaissement",'03_FLUX'!$F$3:$F$502,"Réalisé") | F51: =F50+D51-E51+B51-C51 | G51: ='02_PARAMETRES'!B8 | H51: =IF(F51<G51,"ALERTE",IF(F51<G51*1.2,"VIGILANCE","NORMAL"))
A52: =A51+1 | B52: =SUMIFS('03_FLUX'!$E$3:$E$502,'03_FLUX'!$A$3:$A$502,A52,'03_FLUX'!$B$3:$B$502,"Encaissement",'03_FLUX'!$F$3:$F$502,"Prévu") | C52: =SUMIFS('03_FLUX'!$E$3:$E$502,'03_FLUX'!$A$3:$A$502,A52,'03_FLUX'!$B$3:$B$502,"Décaissement",'03_FLUX'!$F$3:$F$502,"Prévu") | D52: =SUMIFS('03_FLUX'!$E$3:$E$502,'03_FLUX'!$A$3:$A$502,A52,'03_FLUX'!$B$3:$B$502,"Encaissement",'03_FLUX'!$F$3:$F$502,"Réalisé") | E52: =SUMIFS('03_FLUX'!$E$3:$E$502,'03_FLUX'!$A$3:$A$502,A52,'03_FLUX'!$B$3:$B$502,"Décaissement",'03_FLUX'!$F$3:$F$502,"Réalisé") | F52: =F51+D52-E52+B52-C52 | G52: ='02_PARAMETRES'!B8 | H52: =IF(F52<G52,"ALERTE",IF(F52<G52*1.2,"VIGILANCE","NORMAL"))
A53: =A52+1 | B53: =SUMIFS('03_FLUX'!$E$3:$E$502,'03_FLUX'!$A$3:$A$502,A53,'03_FLUX'!$B$3:$B$502,"Encaissement",'03_FLUX'!$F$3:$F$502,"Prévu") | C53: =SUMIFS('03_FLUX'!$E$3:$E$502,'03_FLUX'!$A$3:$A$502,A53,'03_FLUX'!$B$3:$B$502,"Décaissement",'03_FLUX'!$F$3:$F$502,"Prévu") | D53: =SUMIFS('03_FLUX'!$E$3:$E$502,'03_FLUX'!$A$3:$A$502,A53,'03_FLUX'!$B$3:$B$502,"Encaissement",'03_FLUX'!$F$3:$F$502,"Réalisé") | E53: =SUMIFS('03_FLUX'!$E$3:$E$502,'03_FLUX'!$A$3:$A$502,A53,'03_FLUX'!$B$3:$B$502,"Décaissement",'03_FLUX'!$F$3:$F$502,"Réalisé") | F53: =F52+D53-E53+B53-C53 | G53: ='02_PARAMETRES'!B8 | H53: =IF(F53<G53,"ALERTE",IF(F53<G53*1.2,"VIGILANCE","NORMAL"))
A54: =A53+1 | B54: =SUMIFS('03_FLUX'!$E$3:$E$502,'03_FLUX'!$A$3:$A$502,A54,'03_FLUX'!$B$3:$B$502,"Encaissement",'03_FLUX'!$F$3:$F$502,"Prévu") | C54: =SUMIFS('03_FLUX'!$E$3:$E$502,'03_FLUX'!$A$3:$A$502,A54,'03_FLUX'!$B$3:$B$502,"Décaissement",'03_FLUX'!$F$3:$F$502,"Prévu") | D54: =SUMIFS('03_FLUX'!$E$3:$E$502,'03_FLUX'!$A$3:$A$502,A54,'03_FLUX'!$B$3:$B$502,"Encaissement",'03_FLUX'!$F$3:$F$502,"Réalisé") | E54: =SUMIFS('03_FLUX'!$E$3:$E$502,'03_FLUX'!$A$3:$A$502,A54,'03_FLUX'!$B$3:$B$502,"Décaissement",'03_FLUX'!$F$3:$F$502,"Réalisé") | F54: =F53+D54-E54+B54-C54 | G54: ='02_PARAMETRES'!B8 | H54: =IF(F54<G54,"ALERTE",IF(F54<G54*1.2,"VIGILANCE","NORMAL"))
A55: =A54+1 | B55: =SUMIFS('03_FLUX'!$E$3:$E$502,'03_FLUX'!$A$3:$A$502,A55,'03_FLUX'!$B$3:$B$502,"Encaissement",'03_FLUX'!$F$3:$F$502,"Prévu") | C55: =SUMIFS('03_FLUX'!$E$3:$E$502,'03_FLUX'!$A$3:$A$502,A55,'03_FLUX'!$B$3:$B$502,"Décaissement",'03_FLUX'!$F$3:$F$502,"Prévu") | D55: =SUMIFS('03_FLUX'!$E$3:$E$502,'03_FLUX'!$A$3:$A$502,A55,'03_FLUX'!$B$3:$B$502,"Encaissement",'03_FLUX'!$F$3:$F$502,"Réalisé") | E55: =SUMIFS('03_FLUX'!$E$3:$E$502,'03_FLUX'!$A$3:$A$502,A55,'03_FLUX'!$B$3:$B$502,"Décaissement",'03_FLUX'!$F$3:$F$502,"Réalisé") | F55: =F54+D55-E55+B55-C55 | G55: ='02_PARAMETRES'!B8 | H55: =IF(F55<G55,"ALERTE",IF(F55<G55*1.2,"VIGILANCE","NORMAL"))
A56: =A55+1 | B56: =SUMIFS('03_FLUX'!$E$3:$E$502,'03_FLUX'!$A$3:$A$502,A56,'03_FLUX'!$B$3:$B$502,"Encaissement",'03_FLUX'!$F$3:$F$502,"Prévu") | C56: =SUMIFS('03_FLUX'!$E$3:$E$502,'03_FLUX'!$A$3:$A$502,A56,'03_FLUX'!$B$3:$B$502,"Décaissement",'03_FLUX'!$F$3:$F$502,"Prévu") | D56: =SUMIFS('03_FLUX'!$E$3:$E$502,'03_FLUX'!$A$3:$A$502,A56,'03_FLUX'!$B$3:$B$502,"Encaissement",'03_FLUX'!$F$3:$F$502,"Réalisé") | E56: =SUMIFS('03_FLUX'!$E$3:$E$502,'03_FLUX'!$A$3:$A$502,A56,'03_FLUX'!$B$3:$B$502,"Décaissement",'03_FLUX'!$F$3:$F$502,"Réalisé") | F56: =F55+D56-E56+B56-C56 | G56: ='02_PARAMETRES'!B8 | H56: =IF(F56<G56,"ALERTE",IF(F56<G56*1.2,"VIGILANCE","NORMAL"))
A57: =A56+1 | B57: =SUMIFS('03_FLUX'!$E$3:$E$502,'03_FLUX'!$A$3:$A$502,A57,'03_FLUX'!$B$3:$B$502,"Encaissement",'03_FLUX'!$F$3:$F$502,"Prévu") | C57: =SUMIFS('03_FLUX'!$E$3:$E$502,'03_FLUX'!$A$3:$A$502,A57,'03_FLUX'!$B$3:$B$502,"Décaissement",'03_FLUX'!$F$3:$F$502,"Prévu") | D57: =SUMIFS('03_FLUX'!$E$3:$E$502,'03_FLUX'!$A$3:$A$502,A57,'03_FLUX'!$B$3:$B$502,"Encaissement",'03_FLUX'!$F$3:$F$502,"Réalisé") | E57: =SUMIFS('03_FLUX'!$E$3:$E$502,'03_FLUX'!$A$3:$A$502,A57,'03_FLUX'!$B$3:$B$502,"Décaissement",'03_FLUX'!$F$3:$F$502,"Réalisé") | F57: =F56+D57-E57+B57-C57 | G57: ='02_PARAMETRES'!B8 | H57: =IF(F57<G57,"ALERTE",IF(F57<G57*1.2,"VIGILANCE","NORMAL"))
A58: =A57+1 | B58: =SUMIFS('03_FLUX'!$E$3:$E$502,'03_FLUX'!$A$3:$A$502,A58,'03_FLUX'!$B$3:$B$502,"Encaissement",'03_FLUX'!$F$3:$F$502,"Prévu") | C58: =SUMIFS('03_FLUX'!$E$3:$E$502,'03_FLUX'!$A$3:$A$502,A58,'03_FLUX'!$B$3:$B$502,"Décaissement",'03_FLUX'!$F$3:$F$502,"Prévu") | D58: =SUMIFS('03_FLUX'!$E$3:$E$502,'03_FLUX'!$A$3:$A$502,A58,'03_FLUX'!$B$3:$B$502,"Encaissement",'03_FLUX'!$F$3:$F$502,"Réalisé") | E58: =SUMIFS('03_FLUX'!$E$3:$E$502,'03_FLUX'!$A$3:$A$502,A58,'03_FLUX'!$B$3:$B$502,"Décaissement",'03_FLUX'!$F$3:$F$502,"Réalisé") | F58: =F57+D58-E58+B58-C58 | G58: ='02_PARAMETRES'!B8 | H58: =IF(F58<G58,"ALERTE",IF(F58<G58*1.2,"VIGILANCE","NORMAL"))
A59: =A58+1 | B59: =SUMIFS('03_FLUX'!$E$3:$E$502,'03_FLUX'!$A$3:$A$502,A59,'03_FLUX'!$B$3:$B$502,"Encaissement",'03_FLUX'!$F$3:$F$502,"Prévu") | C59: =SUMIFS('03_FLUX'!$E$3:$E$502,'03_FLUX'!$A$3:$A$502,A59,'03_FLUX'!$B$3:$B$502,"Décaissement",'03_FLUX'!$F$3:$F$502,"Prévu") | D59: =SUMIFS('03_FLUX'!$E$3:$E$502,'03_FLUX'!$A$3:$A$502,A59,'03_FLUX'!$B$3:$B$502,"Encaissement",'03_FLUX'!$F$3:$F$502,"Réalisé") | E59: =SUMIFS('03_FLUX'!$E$3:$E$502,'03_FLUX'!$A$3:$A$502,A59,'03_FLUX'!$B$3:$B$502,"Décaissement",'03_FLUX'!$F$3:$F$502,"Réalisé") | F59: =F58+D59-E59+B59-C59 | G59: ='02_PARAMETRES'!B8 | H59: =IF(F59<G59,"ALERTE",IF(F59<G59*1.2,"VIGILANCE","NORMAL"))
A60: =A59+1 | B60: =SUMIFS('03_FLUX'!$E$3:$E$502,'03_FLUX'!$A$3:$A$502,A60,'03_FLUX'!$B$3:$B$502,"Encaissement",'03_FLUX'!$F$3:$F$502,"Prévu") | C60: =SUMIFS('03_FLUX'!$E$3:$E$502,'03_FLUX'!$A$3:$A$502,A60,'03_FLUX'!$B$3:$B$502,"Décaissement",'03_FLUX'!$F$3:$F$502,"Prévu") | D60: =SUMIFS('03_FLUX'!$E$3:$E$502,'03_FLUX'!$A$3:$A$502,A60,'03_FLUX'!$B$3:$B$502,"Encaissement",'03_FLUX'!$F$3:$F$502,"Réalisé") | E60: =SUMIFS('03_FLUX'!$E$3:$E$502,'03_FLUX'!$A$3:$A$502,A60,'03_FLUX'!$B$3:$B$502,"Décaissement",'03_FLUX'!$F$3:$F$502,"Réalisé") | F60: =F59+D60-E60+B60-C60 | G60: ='02_PARAMETRES'!B8 | H60: =IF(F60<G60,"ALERTE",IF(F60<G60*1.2,"VIGILANCE","NORMAL"))
A61: =A60+1 | B61: =SUMIFS('03_FLUX'!$E$3:$E$502,'03_FLUX'!$A$3:$A$502,A61,'03_FLUX'!$B$3:$B$502,"Encaissement",'03_FLUX'!$F$3:$F$502,"Prévu") | C61: =SUMIFS('03_FLUX'!$E$3:$E$502,'03_FLUX'!$A$3:$A$502,A61,'03_FLUX'!$B$3:$B$502,"Décaissement",'03_FLUX'!$F$3:$F$502,"Prévu") | D61: =SUMIFS('03_FLUX'!$E$3:$E$502,'03_FLUX'!$A$3:$A$502,A61,'03_FLUX'!$B$3:$B$502,"Encaissement",'03_FLUX'!$F$3:$F$502,"Réalisé") | E61: =SUMIFS('03_FLUX'!$E$3:$E$502,'03_FLUX'!$A$3:$A$502,A61,'03_FLUX'!$B$3:$B$502,"Décaissement",'03_FLUX'!$F$3:$F$502,"Réalisé") | F61: =F60+D61-E61+B61-C61 | G61: ='02_PARAMETRES'!B8 | H61: =IF(F61<G61,"ALERTE",IF(F61<G61*1.2,"VIGILANCE","NORMAL"))
A62: =A61+1 | B62: =SUMIFS('03_FLUX'!$E$3:$E$502,'03_FLUX'!$A$3:$A$502,A62,'03_FLUX'!$B$3:$B$502,"Encaissement",'03_FLUX'!$F$3:$F$502,"Prévu") | C62: =SUMIFS('03_FLUX'!$E$3:$E$502,'03_FLUX'!$A$3:$A$502,A62,'03_FLUX'!$B$3:$B$502,"Décaissement",'03_FLUX'!$F$3:$F$502,"Prévu") | D62: =SUMIFS('03_FLUX'!$E$3:$E$502,'03_FLUX'!$A$3:$A$502,A62,'03_FLUX'!$B$3:$B$502,"Encaissement",'03_FLUX'!$F$3:$F$502,"Réalisé") | E62: =SUMIFS('03_FLUX'!$E$3:$E$502,'03_FLUX'!$A$3:$A$502,A62,'03_FLUX'!$B$3:$B$502,"Décaissement",'03_FLUX'!$F$3:$F$502,"Réalisé") | F62: =F61+D62-E62+B62-C62 | G62: ='02_PARAMETRES'!B8 | H62: =IF(F62<G62,"ALERTE",IF(F62<G62*1.2,"VIGILANCE","NORMAL"))
A63: =A62+1 | B63: =SUMIFS('03_FLUX'!$E$3:$E$502,'03_FLUX'!$A$3:$A$502,A63,'03_FLUX'!$B$3:$B$502,"Encaissement",'03_FLUX'!$F$3:$F$502,"Prévu") | C63: =SUMIFS('03_FLUX'!$E$3:$E$502,'03_FLUX'!$A$3:$A$502,A63,'03_FLUX'!$B$3:$B$502,"Décaissement",'03_FLUX'!$F$3:$F$502,"Prévu") | D63: =SUMIFS('03_FLUX'!$E$3:$E$502,'03_FLUX'!$A$3:$A$502,A63,'03_FLUX'!$B$3:$B$502,"Encaissement",'03_FLUX'!$F$3:$F$502,"Réalisé") | E63: =SUMIFS('03_FLUX'!$E$3:$E$502,'03_FLUX'!$A$3:$A$502,A63,'03_FLUX'!$B$3:$B$502,"Décaissement",'03_FLUX'!$F$3:$F$502,"Réalisé") | F63: =F62+D63-E63+B63-C63 | G63: ='02_PARAMETRES'!B8 | H63: =IF(F63<G63,"ALERTE",IF(F63<G63*1.2,"VIGILANCE","NORMAL"))
A64: =A63+1 | B64: =SUMIFS('03_FLUX'!$E$3:$E$502,'03_FLUX'!$A$3:$A$502,A64,'03_FLUX'!$B$3:$B$502,"Encaissement",'03_FLUX'!$F$3:$F$502,"Prévu") | C64: =SUMIFS('03_FLUX'!$E$3:$E$502,'03_FLUX'!$A$3:$A$502,A64,'03_FLUX'!$B$3:$B$502,"Décaissement",'03_FLUX'!$F$3:$F$502,"Prévu") | D64: =SUMIFS('03_FLUX'!$E$3:$E$502,'03_FLUX'!$A$3:$A$502,A64,'03_FLUX'!$B$3:$B$502,"Encaissement",'03_FLUX'!$F$3:$F$502,"Réalisé") | E64: =SUMIFS('03_FLUX'!$E$3:$E$502,'03_FLUX'!$A$3:$A$502,A64,'03_FLUX'!$B$3:$B$502,"Décaissement",'03_FLUX'!$F$3:$F$502,"Réalisé") | F64: =F63+D64-E64+B64-C64 | G64: ='02_PARAMETRES'!B8 | H64: =IF(F64<G64,"ALERTE",IF(F64<G64*1.2,"VIGILANCE","NORMAL"))
A65: =A64+1 | B65: =SUMIFS('03_FLUX'!$E$3:$E$502,'03_FLUX'!$A$3:$A$502,A65,'03_FLUX'!$B$3:$B$502,"Encaissement",'03_FLUX'!$F$3:$F$502,"Prévu") | C65: =SUMIFS('03_FLUX'!$E$3:$E$502,'03_FLUX'!$A$3:$A$502,A65,'03_FLUX'!$B$3:$B$502,"Décaissement",'03_FLUX'!$F$3:$F$502,"Prévu") | D65: =SUMIFS('03_FLUX'!$E$3:$E$502,'03_FLUX'!$A$3:$A$502,A65,'03_FLUX'!$B$3:$B$502,"Encaissement",'03_FLUX'!$F$3:$F$502,"Réalisé") | E65: =SUMIFS('03_FLUX'!$E$3:$E$502,'03_FLUX'!$A$3:$A$502,A65,'03_FLUX'!$B$3:$B$502,"Décaissement",'03_FLUX'!$F$3:$F$502,"Réalisé") | F65: =F64+D65-E65+B65-C65 | G65: ='02_PARAMETRES'!B8 | H65: =IF(F65<G65,"ALERTE",IF(F65<G65*1.2,"VIGILANCE","NORMAL"))
A66: =A65+1 | B66: =SUMIFS('03_FLUX'!$E$3:$E$502,'03_FLUX'!$A$3:$A$502,A66,'03_FLUX'!$B$3:$B$502,"Encaissement",'03_FLUX'!$F$3:$F$502,"Prévu") | C66: =SUMIFS('03_FLUX'!$E$3:$E$502,'03_FLUX'!$A$3:$A$502,A66,'03_FLUX'!$B$3:$B$502,"Décaissement",'03_FLUX'!$F$3:$F$502,"Prévu") | D66: =SUMIFS('03_FLUX'!$E$3:$E$502,'03_FLUX'!$A$3:$A$502,A66,'03_FLUX'!$B$3:$B$502,"Encaissement",'03_FLUX'!$F$3:$F$502,"Réalisé") | E66: =SUMIFS('03_FLUX'!$E$3:$E$502,'03_FLUX'!$A$3:$A$502,A66,'03_FLUX'!$B$3:$B$502,"Décaissement",'03_FLUX'!$F$3:$F$502,"Réalisé") | F66: =F65+D66-E66+B66-C66 | G66: ='02_PARAMETRES'!B8 | H66: =IF(F66<G66,"ALERTE",IF(F66<G66*1.2,"VIGILANCE","NORMAL"))
A67: =A66+1 | B67: =SUMIFS('03_FLUX'!$E$3:$E$502,'03_FLUX'!$A$3:$A$502,A67,'03_FLUX'!$B$3:$B$502,"Encaissement",'03_FLUX'!$F$3:$F$502,"Prévu") | C67: =SUMIFS('03_FLUX'!$E$3:$E$502,'03_FLUX'!$A$3:$A$502,A67,'03_FLUX'!$B$3:$B$502,"Décaissement",'03_FLUX'!$F$3:$F$502,"Prévu") | D67: =SUMIFS('03_FLUX'!$E$3:$E$502,'03_FLUX'!$A$3:$A$502,A67,'03_FLUX'!$B$3:$B$502,"Encaissement",'03_FLUX'!$F$3:$F$502,"Réalisé") | E67: =SUMIFS('03_FLUX'!$E$3:$E$502,'03_FLUX'!$A$3:$A$502,A67,'03_FLUX'!$B$3:$B$502,"Décaissement",'03_FLUX'!$F$3:$F$502,"Réalisé") | F67: =F66+D67-E67+B67-C67 | G67: ='02_PARAMETRES'!B8 | H67: =IF(F67<G67,"ALERTE",IF(F67<G67*1.2,"VIGILANCE","NORMAL"))
A68: =A67+1 | B68: =SUMIFS('03_FLUX'!$E$3:$E$502,'03_FLUX'!$A$3:$A$502,A68,'03_FLUX'!$B$3:$B$502,"Encaissement",'03_FLUX'!$F$3:$F$502,"Prévu") | C68: =SUMIFS('03_FLUX'!$E$3:$E$502,'03_FLUX'!$A$3:$A$502,A68,'03_FLUX'!$B$3:$B$502,"Décaissement",'03_FLUX'!$F$3:$F$502,"Prévu") | D68: =SUMIFS('03_FLUX'!$E$3:$E$502,'03_FLUX'!$A$3:$A$502,A68,'03_FLUX'!$B$3:$B$502,"Encaissement",'03_FLUX'!$F$3:$F$502,"Réalisé") | E68: =SUMIFS('03_FLUX'!$E$3:$E$502,'03_FLUX'!$A$3:$A$502,A68,'03_FLUX'!$B$3:$B$502,"Décaissement",'03_FLUX'!$F$3:$F$502,"Réalisé") | F68: =F67+D68-E68+B68-C68 | G68: ='02_PARAMETRES'!B8 | H68: =IF(F68<G68,"ALERTE",IF(F68<G68*1.2,"VIGILANCE","NORMAL"))
A69: =A68+1 | B69: =SUMIFS('03_FLUX'!$E$3:$E$502,'03_FLUX'!$A$3:$A$502,A69,'03_FLUX'!$B$3:$B$502,"Encaissement",'03_FLUX'!$F$3:$F$502,"Prévu") | C69: =SUMIFS('03_FLUX'!$E$3:$E$502,'03_FLUX'!$A$3:$A$502,A69,'03_FLUX'!$B$3:$B$502,"Décaissement",'03_FLUX'!$F$3:$F$502,"Prévu") | D69: =SUMIFS('03_FLUX'!$E$3:$E$502,'03_FLUX'!$A$3:$A$502,A69,'03_FLUX'!$B$3:$B$502,"Encaissement",'03_FLUX'!$F$3:$F$502,"Réalisé") | E69: =SUMIFS('03_FLUX'!$E$3:$E$502,'03_FLUX'!$A$3:$A$502,A69,'03_FLUX'!$B$3:$B$502,"Décaissement",'03_FLUX'!$F$3:$F$502,"Réalisé") | F69: =F68+D69-E69+B69-C69 | G69: ='02_PARAMETRES'!B8 | H69: =IF(F69<G69,"ALERTE",IF(F69<G69*1.2,"VIGILANCE","NORMAL"))
A70: =A69+1 | B70: =SUMIFS('03_FLUX'!$E$3:$E$502,'03_FLUX'!$A$3:$A$502,A70,'03_FLUX'!$B$3:$B$502,"Encaissement",'03_FLUX'!$F$3:$F$502,"Prévu") | C70: =SUMIFS('03_FLUX'!$E$3:$E$502,'03_FLUX'!$A$3:$A$502,A70,'03_FLUX'!$B$3:$B$502,"Décaissement",'03_FLUX'!$F$3:$F$502,"Prévu") | D70: =SUMIFS('03_FLUX'!$E$3:$E$502,'03_FLUX'!$A$3:$A$502,A70,'03_FLUX'!$B$3:$B$502,"Encaissement",'03_FLUX'!$F$3:$F$502,"Réalisé") | E70: =SUMIFS('03_FLUX'!$E$3:$E$502,'03_FLUX'!$A$3:$A$502,A70,'03_FLUX'!$B$3:$B$502,"Décaissement",'03_FLUX'!$F$3:$F$502,"Réalisé") | F70: =F69+D70-E70+B70-C70 | G70: ='02_PARAMETRES'!B8 | H70: =IF(F70<G70,"ALERTE",IF(F70<G70*1.2,"VIGILANCE","NORMAL"))
A71: =A70+1 | B71: =SUMIFS('03_FLUX'!$E$3:$E$502,'03_FLUX'!$A$3:$A$502,A71,'03_FLUX'!$B$3:$B$502,"Encaissement",'03_FLUX'!$F$3:$F$502,"Prévu") | C71: =SUMIFS('03_FLUX'!$E$3:$E$502,'03_FLUX'!$A$3:$A$502,A71,'03_FLUX'!$B$3:$B$502,"Décaissement",'03_FLUX'!$F$3:$F$502,"Prévu") | D71: =SUMIFS('03_FLUX'!$E$3:$E$502,'03_FLUX'!$A$3:$A$502,A71,'03_FLUX'!$B$3:$B$502,"Encaissement",'03_FLUX'!$F$3:$F$502,"Réalisé") | E71: =SUMIFS('03_FLUX'!$E$3:$E$502,'03_FLUX'!$A$3:$A$502,A71,'03_FLUX'!$B$3:$B$502,"Décaissement",'03_FLUX'!$F$3:$F$502,"Réalisé") | F71: =F70+D71-E71+B71-C71 | G71: ='02_PARAMETRES'!B8 | H71: =IF(F71<G71,"ALERTE",IF(F71<G71*1.2,"VIGILANCE","NORMAL"))
A72: =A71+1 | B72: =SUMIFS('03_FLUX'!$E$3:$E$502,'03_FLUX'!$A$3:$A$502,A72,'03_FLUX'!$B$3:$B$502,"Encaissement",'03_FLUX'!$F$3:$F$502,"Prévu") | C72: =SUMIFS('03_FLUX'!$E$3:$E$502,'03_FLUX'!$A$3:$A$502,A72,'03_FLUX'!$B$3:$B$502,"Décaissement",'03_FLUX'!$F$3:$F$502,"Prévu") | D72: =SUMIFS('03_FLUX'!$E$3:$E$502,'03_FLUX'!$A$3:$A$502,A72,'03_FLUX'!$B$3:$B$502,"Encaissement",'03_FLUX'!$F$3:$F$502,"Réalisé") | E72: =SUMIFS('03_FLUX'!$E$3:$E$502,'03_FLUX'!$A$3:$A$502,A72,'03_FLUX'!$B$3:$B$502,"Décaissement",'03_FLUX'!$F$3:$F$502,"Réalisé") | F72: =F71+D72-E72+B72-C72 | G72: ='02_PARAMETRES'!B8 | H72: =IF(F72<G72,"ALERTE",IF(F72<G72*1.2,"VIGILANCE","NORMAL"))
A73: =A72+1 | B73: =SUMIFS('03_FLUX'!$E$3:$E$502,'03_FLUX'!$A$3:$A$502,A73,'03_FLUX'!$B$3:$B$502,"Encaissement",'03_FLUX'!$F$3:$F$502,"Prévu") | C73: =SUMIFS('03_FLUX'!$E$3:$E$502,'03_FLUX'!$A$3:$A$502,A73,'03_FLUX'!$B$3:$B$502,"Décaissement",'03_FLUX'!$F$3:$F$502,"Prévu") | D73: =SUMIFS('03_FLUX'!$E$3:$E$502,'03_FLUX'!$A$3:$A$502,A73,'03_FLUX'!$B$3:$B$502,"Encaissement",'03_FLUX'!$F$3:$F$502,"Réalisé") | E73: =SUMIFS('03_FLUX'!$E$3:$E$502,'03_FLUX'!$A$3:$A$502,A73,'03_FLUX'!$B$3:$B$502,"Décaissement",'03_FLUX'!$F$3:$F$502,"Réalisé") | F73: =F72+D73-E73+B73-C73 | G73: ='02_PARAMETRES'!B8 | H73: =IF(F73<G73,"ALERTE",IF(F73<G73*1.2,"VIGILANCE","NORMAL"))
A74: =A73+1 | B74: =SUMIFS('03_FLUX'!$E$3:$E$502,'03_FLUX'!$A$3:$A$502,A74,'03_FLUX'!$B$3:$B$502,"Encaissement",'03_FLUX'!$F$3:$F$502,"Prévu") | C74: =SUMIFS('03_FLUX'!$E$3:$E$502,'03_FLUX'!$A$3:$A$502,A74,'03_FLUX'!$B$3:$B$502,"Décaissement",'03_FLUX'!$F$3:$F$502,"Prévu") | D74: =SUMIFS('03_FLUX'!$E$3:$E$502,'03_FLUX'!$A$3:$A$502,A74,'03_FLUX'!$B$3:$B$502,"Encaissement",'03_FLUX'!$F$3:$F$502,"Réalisé") | E74: =SUMIFS('03_FLUX'!$E$3:$E$502,'03_FLUX'!$A$3:$A$502,A74,'03_FLUX'!$B$3:$B$502,"Décaissement",'03_FLUX'!$F$3:$F$502,"Réalisé") | F74: =F73+D74-E74+B74-C74 | G74: ='02_PARAMETRES'!B8 | H74: =IF(F74<G74,"ALERTE",IF(F74<G74*1.2,"VIGILANCE","NORMAL"))
A75: =A74+1 | B75: =SUMIFS('03_FLUX'!$E$3:$E$502,'03_FLUX'!$A$3:$A$502,A75,'03_FLUX'!$B$3:$B$502,"Encaissement",'03_FLUX'!$F$3:$F$502,"Prévu") | C75: =SUMIFS('03_FLUX'!$E$3:$E$502,'03_FLUX'!$A$3:$A$502,A75,'03_FLUX'!$B$3:$B$502,"Décaissement",'03_FLUX'!$F$3:$F$502,"Prévu") | D75: =SUMIFS('03_FLUX'!$E$3:$E$502,'03_FLUX'!$A$3:$A$502,A75,'03_FLUX'!$B$3:$B$502,"Encaissement",'03_FLUX'!$F$3:$F$502,"Réalisé") | E75: =SUMIFS('03_FLUX'!$E$3:$E$502,'03_FLUX'!$A$3:$A$502,A75,'03_FLUX'!$B$3:$B$502,"Décaissement",'03_FLUX'!$F$3:$F$502,"Réalisé") | F75: =F74+D75-E75+B75-C75 | G75: ='02_PARAMETRES'!B8 | H75: =IF(F75<G75,"ALERTE",IF(F75<G75*1.2,"VIGILANCE","NORMAL"))
A76: =A75+1 | B76: =SUMIFS('03_FLUX'!$E$3:$E$502,'03_FLUX'!$A$3:$A$502,A76,'03_FLUX'!$B$3:$B$502,"Encaissement",'03_FLUX'!$F$3:$F$502,"Prévu") | C76: =SUMIFS('03_FLUX'!$E$3:$E$502,'03_FLUX'!$A$3:$A$502,A76,'03_FLUX'!$B$3:$B$502,"Décaissement",'03_FLUX'!$F$3:$F$502,"Prévu") | D76: =SUMIFS('03_FLUX'!$E$3:$E$502,'03_FLUX'!$A$3:$A$502,A76,'03_FLUX'!$B$3:$B$502,"Encaissement",'03_FLUX'!$F$3:$F$502,"Réalisé") | E76: =SUMIFS('03_FLUX'!$E$3:$E$502,'03_FLUX'!$A$3:$A$502,A76,'03_FLUX'!$B$3:$B$502,"Décaissement",'03_FLUX'!$F$3:$F$502,"Réalisé") | F76: =F75+D76-E76+B76-C76 | G76: ='02_PARAMETRES'!B8 | H76: =IF(F76<G76,"ALERTE",IF(F76<G76*1.2,"VIGILANCE","NORMAL"))
A77: =A76+1 | B77: =SUMIFS('03_FLUX'!$E$3:$E$502,'03_FLUX'!$A$3:$A$502,A77,'03_FLUX'!$B$3:$B$502,"Encaissement",'03_FLUX'!$F$3:$F$502,"Prévu") | C77: =SUMIFS('03_FLUX'!$E$3:$E$502,'03_FLUX'!$A$3:$A$502,A77,'03_FLUX'!$B$3:$B$502,"Décaissement",'03_FLUX'!$F$3:$F$502,"Prévu") | D77: =SUMIFS('03_FLUX'!$E$3:$E$502,'03_FLUX'!$A$3:$A$502,A77,'03_FLUX'!$B$3:$B$502,"Encaissement",'03_FLUX'!$F$3:$F$502,"Réalisé") | E77: =SUMIFS('03_FLUX'!$E$3:$E$502,'03_FLUX'!$A$3:$A$502,A77,'03_FLUX'!$B$3:$B$502,"Décaissement",'03_FLUX'!$F$3:$F$502,"Réalisé") | F77: =F76+D77-E77+B77-C77 | G77: ='02_PARAMETRES'!B8 | H77: =IF(F77<G77,"ALERTE",IF(F77<G77*1.2,"VIGILANCE","NORMAL"))
A78: =A77+1 | B78: =SUMIFS('03_FLUX'!$E$3:$E$502,'03_FLUX'!$A$3:$A$502,A78,'03_FLUX'!$B$3:$B$502,"Encaissement",'03_FLUX'!$F$3:$F$502,"Prévu") | C78: =SUMIFS('03_FLUX'!$E$3:$E$502,'03_FLUX'!$A$3:$A$502,A78,'03_FLUX'!$B$3:$B$502,"Décaissement",'03_FLUX'!$F$3:$F$502,"Prévu") | D78: =SUMIFS('03_FLUX'!$E$3:$E$502,'03_FLUX'!$A$3:$A$502,A78,'03_FLUX'!$B$3:$B$502,"Encaissement",'03_FLUX'!$F$3:$F$502,"Réalisé") | E78: =SUMIFS('03_FLUX'!$E$3:$E$502,'03_FLUX'!$A$3:$A$502,A78,'03_FLUX'!$B$3:$B$502,"Décaissement",'03_FLUX'!$F$3:$F$502,"Réalisé") | F78: =F77+D78-E78+B78-C78 | G78: ='02_PARAMETRES'!B8 | H78: =IF(F78<G78,"ALERTE",IF(F78<G78*1.2,"VIGILANCE","NORMAL"))
A79: =A78+1 | B79: =SUMIFS('03_FLUX'!$E$3:$E$502,'03_FLUX'!$A$3:$A$502,A79,'03_FLUX'!$B$3:$B$502,"Encaissement",'03_FLUX'!$F$3:$F$502,"Prévu") | C79: =SUMIFS('03_FLUX'!$E$3:$E$502,'03_FLUX'!$A$3:$A$502,A79,'03_FLUX'!$B$3:$B$502,"Décaissement",'03_FLUX'!$F$3:$F$502,"Prévu") | D79: =SUMIFS('03_FLUX'!$E$3:$E$502,'03_FLUX'!$A$3:$A$502,A79,'03_FLUX'!$B$3:$B$502,"Encaissement",'03_FLUX'!$F$3:$F$502,"Réalisé") | E79: =SUMIFS('03_FLUX'!$E$3:$E$502,'03_FLUX'!$A$3:$A$502,A79,'03_FLUX'!$B$3:$B$502,"Décaissement",'03_FLUX'!$F$3:$F$502,"Réalisé") | F79: =F78+D79-E79+B79-C79 | G79: ='02_PARAMETRES'!B8 | H79: =IF(F79<G79,"ALERTE",IF(F79<G79*1.2,"VIGILANCE","NORMAL"))
A80: =A79+1 | B80: =SUMIFS('03_FLUX'!$E$3:$E$502,'03_FLUX'!$A$3:$A$502,A80,'03_FLUX'!$B$3:$B$502,"Encaissement",'03_FLUX'!$F$3:$F$502,"Prévu") | C80: =SUMIFS('03_FLUX'!$E$3:$E$502,'03_FLUX'!$A$3:$A$502,A80,'03_FLUX'!$B$3:$B$502,"Décaissement",'03_FLUX'!$F$3:$F$502,"Prévu") | D80: =SUMIFS('03_FLUX'!$E$3:$E$502,'03_FLUX'!$A$3:$A$502,A80,'03_FLUX'!$B$3:$B$502,"Encaissement",'03_FLUX'!$F$3:$F$502,"Réalisé") | E80: =SUMIFS('03_FLUX'!$E$3:$E$502,'03_FLUX'!$A$3:$A$502,A80,'03_FLUX'!$B$3:$B$502,"Décaissement",'03_FLUX'!$F$3:$F$502,"Réalisé") | F80: =F79+D80-E80+B80-C80 | G80: ='02_PARAMETRES'!B8 | H80: =IF(F80<G80,"ALERTE",IF(F80<G80*1.2,"VIGILANCE","NORMAL"))
A81: =A80+1 | B81: =SUMIFS('03_FLUX'!$E$3:$E$502,'03_FLUX'!$A$3:$A$502,A81,'03_FLUX'!$B$3:$B$502,"Encaissement",'03_FLUX'!$F$3:$F$502,"Prévu") | C81: =SUMIFS('03_FLUX'!$E$3:$E$502,'03_FLUX'!$A$3:$A$502,A81,'03_FLUX'!$B$3:$B$502,"Décaissement",'03_FLUX'!$F$3:$F$502,"Prévu") | D81: =SUMIFS('03_FLUX'!$E$3:$E$502,'03_FLUX'!$A$3:$A$502,A81,'03_FLUX'!$B$3:$B$502,"Encaissement",'03_FLUX'!$F$3:$F$502,"Réalisé") | E81: =SUMIFS('03_FLUX'!$E$3:$E$502,'03_FLUX'!$A$3:$A$502,A81,'03_FLUX'!$B$3:$B$502,"Décaissement",'03_FLUX'!$F$3:$F$502,"Réalisé") | F81: =F80+D81-E81+B81-C81 | G81: ='02_PARAMETRES'!B8 | H81: =IF(F81<G81,"ALERTE",IF(F81<G81*1.2,"VIGILANCE","NORMAL"))
A82: =A81+1 | B82: =SUMIFS('03_FLUX'!$E$3:$E$502,'03_FLUX'!$A$3:$A$502,A82,'03_FLUX'!$B$3:$B$502,"Encaissement",'03_FLUX'!$F$3:$F$502,"Prévu") | C82: =SUMIFS('03_FLUX'!$E$3:$E$502,'03_FLUX'!$A$3:$A$502,A82,'03_FLUX'!$B$3:$B$502,"Décaissement",'03_FLUX'!$F$3:$F$502,"Prévu") | D82: =SUMIFS('03_FLUX'!$E$3:$E$502,'03_FLUX'!$A$3:$A$502,A82,'03_FLUX'!$B$3:$B$502,"Encaissement",'03_FLUX'!$F$3:$F$502,"Réalisé") | E82: =SUMIFS('03_FLUX'!$E$3:$E$502,'03_FLUX'!$A$3:$A$502,A82,'03_FLUX'!$B$3:$B$502,"Décaissement",'03_FLUX'!$F$3:$F$502,"Réalisé") | F82: =F81+D82-E82+B82-C82 | G82: ='02_PARAMETRES'!B8 | H82: =IF(F82<G82,"ALERTE",IF(F82<G82*1.2,"VIGILANCE","NORMAL"))
A83: =A82+1 | B83: =SUMIFS('03_FLUX'!$E$3:$E$502,'03_FLUX'!$A$3:$A$502,A83,'03_FLUX'!$B$3:$B$502,"Encaissement",'03_FLUX'!$F$3:$F$502,"Prévu") | C83: =SUMIFS('03_FLUX'!$E$3:$E$502,'03_FLUX'!$A$3:$A$502,A83,'03_FLUX'!$B$3:$B$502,"Décaissement",'03_FLUX'!$F$3:$F$502,"Prévu") | D83: =SUMIFS('03_FLUX'!$E$3:$E$502,'03_FLUX'!$A$3:$A$502,A83,'03_FLUX'!$B$3:$B$502,"Encaissement",'03_FLUX'!$F$3:$F$502,"Réalisé") | E83: =SUMIFS('03_FLUX'!$E$3:$E$502,'03_FLUX'!$A$3:$A$502,A83,'03_FLUX'!$B$3:$B$502,"Décaissement",'03_FLUX'!$F$3:$F$502,"Réalisé") | F83: =F82+D83-E83+B83-C83 | G83: ='02_PARAMETRES'!B8 | H83: =IF(F83<G83,"ALERTE",IF(F83<G83*1.2,"VIGILANCE","NORMAL"))
A84: =A83+1 | B84: =SUMIFS('03_FLUX'!$E$3:$E$502,'03_FLUX'!$A$3:$A$502,A84,'03_FLUX'!$B$3:$B$502,"Encaissement",'03_FLUX'!$F$3:$F$502,"Prévu") | C84: =SUMIFS('03_FLUX'!$E$3:$E$502,'03_FLUX'!$A$3:$A$502,A84,'03_FLUX'!$B$3:$B$502,"Décaissement",'03_FLUX'!$F$3:$F$502,"Prévu") | D84: =SUMIFS('03_FLUX'!$E$3:$E$502,'03_FLUX'!$A$3:$A$502,A84,'03_FLUX'!$B$3:$B$502,"Encaissement",'03_FLUX'!$F$3:$F$502,"Réalisé") | E84: =SUMIFS('03_FLUX'!$E$3:$E$502,'03_FLUX'!$A$3:$A$502,A84,'03_FLUX'!$B$3:$B$502,"Décaissement",'03_FLUX'!$F$3:$F$502,"Réalisé") | F84: =F83+D84-E84+B84-C84 | G84: ='02_PARAMETRES'!B8 | H84: =IF(F84<G84,"ALERTE",IF(F84<G84*1.2,"VIGILANCE","NORMAL"))
A85: =A84+1 | B85: =SUMIFS('03_FLUX'!$E$3:$E$502,'03_FLUX'!$A$3:$A$502,A85,'03_FLUX'!$B$3:$B$502,"Encaissement",'03_FLUX'!$F$3:$F$502,"Prévu") | C85: =SUMIFS('03_FLUX'!$E$3:$E$502,'03_FLUX'!$A$3:$A$502,A85,'03_FLUX'!$B$3:$B$502,"Décaissement",'03_FLUX'!$F$3:$F$502,"Prévu") | D85: =SUMIFS('03_FLUX'!$E$3:$E$502,'03_FLUX'!$A$3:$A$502,A85,'03_FLUX'!$B$3:$B$502,"Encaissement",'03_FLUX'!$F$3:$F$502,"Réalisé") | E85: =SUMIFS('03_FLUX'!$E$3:$E$502,'03_FLUX'!$A$3:$A$502,A85,'03_FLUX'!$B$3:$B$502,"Décaissement",'03_FLUX'!$F$3:$F$502,"Réalisé") | F85: =F84+D85-E85+B85-C85 | G85: ='02_PARAMETRES'!B8 | H85: =IF(F85<G85,"ALERTE",IF(F85<G85*1.2,"VIGILANCE","NORMAL"))
A86: =A85+1 | B86: =SUMIFS('03_FLUX'!$E$3:$E$502,'03_FLUX'!$A$3:$A$502,A86,'03_FLUX'!$B$3:$B$502,"Encaissement",'03_FLUX'!$F$3:$F$502,"Prévu") | C86: =SUMIFS('03_FLUX'!$E$3:$E$502,'03_FLUX'!$A$3:$A$502,A86,'03_FLUX'!$B$3:$B$502,"Décaissement",'03_FLUX'!$F$3:$F$502,"Prévu") | D86: =SUMIFS('03_FLUX'!$E$3:$E$502,'03_FLUX'!$A$3:$A$502,A86,'03_FLUX'!$B$3:$B$502,"Encaissement",'03_FLUX'!$F$3:$F$502,"Réalisé") | E86: =SUMIFS('03_FLUX'!$E$3:$E$502,'03_FLUX'!$A$3:$A$502,A86,'03_FLUX'!$B$3:$B$502,"Décaissement",'03_FLUX'!$F$3:$F$502,"Réalisé") | F86: =F85+D86-E86+B86-C86 | G86: ='02_PARAMETRES'!B8 | H86: =IF(F86<G86,"ALERTE",IF(F86<G86*1.2,"VIGILANCE","NORMAL"))
A87: =A86+1 | B87: =SUMIFS('03_FLUX'!$E$3:$E$502,'03_FLUX'!$A$3:$A$502,A87,'03_FLUX'!$B$3:$B$502,"Encaissement",'03_FLUX'!$F$3:$F$502,"Prévu") | C87: =SUMIFS('03_FLUX'!$E$3:$E$502,'03_FLUX'!$A$3:$A$502,A87,'03_FLUX'!$B$3:$B$502,"Décaissement",'03_FLUX'!$F$3:$F$502,"Prévu") | D87: =SUMIFS('03_FLUX'!$E$3:$E$502,'03_FLUX'!$A$3:$A$502,A87,'03_FLUX'!$B$3:$B$502,"Encaissement",'03_FLUX'!$F$3:$F$502,"Réalisé") | E87: =SUMIFS('03_FLUX'!$E$3:$E$502,'03_FLUX'!$A$3:$A$502,A87,'03_FLUX'!$B$3:$B$502,"Décaissement",'03_FLUX'!$F$3:$F$502,"Réalisé") | F87: =F86+D87-E87+B87-C87 | G87: ='02_PARAMETRES'!B8 | H87: =IF(F87<G87,"ALERTE",IF(F87<G87*1.2,"VIGILANCE","NORMAL"))
A88: =A87+1 | B88: =SUMIFS('03_FLUX'!$E$3:$E$502,'03_FLUX'!$A$3:$A$502,A88,'03_FLUX'!$B$3:$B$502,"Encaissement",'03_FLUX'!$F$3:$F$502,"Prévu") | C88: =SUMIFS('03_FLUX'!$E$3:$E$502,'03_FLUX'!$A$3:$A$502,A88,'03_FLUX'!$B$3:$B$502,"Décaissement",'03_FLUX'!$F$3:$F$502,"Prévu") | D88: =SUMIFS('03_FLUX'!$E$3:$E$502,'03_FLUX'!$A$3:$A$502,A88,'03_FLUX'!$B$3:$B$502,"Encaissement",'03_FLUX'!$F$3:$F$502,"Réalisé") | E88: =SUMIFS('03_FLUX'!$E$3:$E$502,'03_FLUX'!$A$3:$A$502,A88,'03_FLUX'!$B$3:$B$502,"Décaissement",'03_FLUX'!$F$3:$F$502,"Réalisé") | F88: =F87+D88-E88+B88-C88 | G88: ='02_PARAMETRES'!B8 | H88: =IF(F88<G88,"ALERTE",IF(F88<G88*1.2,"VIGILANCE","NORMAL"))
A89: =A88+1 | B89: =SUMIFS('03_FLUX'!$E$3:$E$502,'03_FLUX'!$A$3:$A$502,A89,'03_FLUX'!$B$3:$B$502,"Encaissement",'03_FLUX'!$F$3:$F$502,"Prévu") | C89: =SUMIFS('03_FLUX'!$E$3:$E$502,'03_FLUX'!$A$3:$A$502,A89,'03_FLUX'!$B$3:$B$502,"Décaissement",'03_FLUX'!$F$3:$F$502,"Prévu") | D89: =SUMIFS('03_FLUX'!$E$3:$E$502,'03_FLUX'!$A$3:$A$502,A89,'03_FLUX'!$B$3:$B$502,"Encaissement",'03_FLUX'!$F$3:$F$502,"Réalisé") | E89: =SUMIFS('03_FLUX'!$E$3:$E$502,'03_FLUX'!$A$3:$A$502,A89,'03_FLUX'!$B$3:$B$502,"Décaissement",'03_FLUX'!$F$3:$F$502,"Réalisé") | F89: =F88+D89-E89+B89-C89 | G89: ='02_PARAMETRES'!B8 | H89: =IF(F89<G89,"ALERTE",IF(F89<G89*1.2,"VIGILANCE","NORMAL"))
A90: =A89+1 | B90: =SUMIFS('03_FLUX'!$E$3:$E$502,'03_FLUX'!$A$3:$A$502,A90,'03_FLUX'!$B$3:$B$502,"Encaissement",'03_FLUX'!$F$3:$F$502,"Prévu") | C90: =SUMIFS('03_FLUX'!$E$3:$E$502,'03_FLUX'!$A$3:$A$502,A90,'03_FLUX'!$B$3:$B$502,"Décaissement",'03_FLUX'!$F$3:$F$502,"Prévu") | D90: =SUMIFS('03_FLUX'!$E$3:$E$502,'03_FLUX'!$A$3:$A$502,A90,'03_FLUX'!$B$3:$B$502,"Encaissement",'03_FLUX'!$F$3:$F$502,"Réalisé") | E90: =SUMIFS('03_FLUX'!$E$3:$E$502,'03_FLUX'!$A$3:$A$502,A90,'03_FLUX'!$B$3:$B$502,"Décaissement",'03_FLUX'!$F$3:$F$502,"Réalisé") | F90: =F89+D90-E90+B90-C90 | G90: ='02_PARAMETRES'!B8 | H90: =IF(F90<G90,"ALERTE",IF(F90<G90*1.2,"VIGILANCE","NORMAL"))
A91: =A90+1 | B91: =SUMIFS('03_FLUX'!$E$3:$E$502,'03_FLUX'!$A$3:$A$502,A91,'03_FLUX'!$B$3:$B$502,"Encaissement",'03_FLUX'!$F$3:$F$502,"Prévu") | C91: =SUMIFS('03_FLUX'!$E$3:$E$502,'03_FLUX'!$A$3:$A$502,A91,'03_FLUX'!$B$3:$B$502,"Décaissement",'03_FLUX'!$F$3:$F$502,"Prévu") | D91: =SUMIFS('03_FLUX'!$E$3:$E$502,'03_FLUX'!$A$3:$A$502,A91,'03_FLUX'!$B$3:$B$502,"Encaissement",'03_FLUX'!$F$3:$F$502,"Réalisé") | E91: =SUMIFS('03_FLUX'!$E$3:$E$502,'03_FLUX'!$A$3:$A$502,A91,'03_FLUX'!$B$3:$B$502,"Décaissement",'03_FLUX'!$F$3:$F$502,"Réalisé") | F91: =F90+D91-E91+B91-C91 | G91: ='02_PARAMETRES'!B8 | H91: =IF(F91<G91,"ALERTE",IF(F91<G91*1.2,"VIGILANCE","NORMAL"))

Sheet 06_AIDE
A1: AIDE — TABLEAU DE SUIVI DE TRÉSORERIE
A3: 1. Configurer | B3: Dans 02_PARAMETRES, renseignez le solde initial, sa date et votre seuil de sécurité.
A6: 2. Saisir | B6: Dans 03_FLUX, saisissez chaque flux avec un montant toujours positif. Le type Encaissement ou Décaissement gère le signe automatiquement.
A9: 3. Prévoir | B9: Les flux Prévu alimentent automatiquement la projection quotidienne de 90 jours.
A12: 4. Lire le tableau de bord | B12: Le tableau de bord affiche les soldes à 30, 60 et 90 jours, ainsi que la première date de passage sous le seuil.
A15: 5. Comprendre les alertes | B15: Normal : au-dessus du seuil. Vigilance : à moins de 20 % du seuil. Alerte : sous le seuil de sécurité.

Sheet 99_LISTES
A1: Types | B1: Catégories | C1: Statuts
A2: Encaissement | B2: Ventes | C2: Réalisé
A3: Décaissement | B3: Prestations | C3: Prévu
B4: Acomptes
B5: Autres encaissements
B6: Achats
B7: Fournisseurs
B8: Sous-traitance
B9: Salaires
B10: Charges sociales
B11: Impôts et taxes
B12: TVA
B13: Loyer
B14: Assurances
B15: Énergie
... B21: Autres dépenses
